package android.support.v7.app;

import android.app.Activity;
import android.app.Dialog;
import android.app.UiModeManager;
import android.content.BroadcastReceiver;
import android.content.ComponentName;
import android.content.Context;
import android.content.Intent;
import android.content.IntentFilter;
import android.content.pm.PackageManager;
import android.content.res.Configuration;
import android.content.res.Resources;
import android.content.res.TypedArray;
import android.graphics.Rect;
import android.graphics.drawable.Drawable;
import android.os.Build;
import android.os.Bundle;
import android.os.Parcel;
import android.os.Parcelable;
import android.support.v4.app.NavUtils;
import android.support.v4.view.KeyEventDispatcher;
import android.support.v4.view.LayoutInflaterCompat;
import android.support.v4.view.OnApplyWindowInsetsListener;
import android.support.v4.view.ViewCompat;
import android.support.v4.view.ViewPropertyAnimatorCompat;
import android.support.v4.view.ViewPropertyAnimatorListener;
import android.support.v4.view.ViewPropertyAnimatorListenerAdapter;
import android.support.v4.view.WindowInsetsCompat;
import android.support.v4.widget.PopupWindowCompat;
import android.support.v7.appcompat.R;
import android.support.v7.content.res.AppCompatResources;
import android.support.v7.view.ActionMode;
import android.support.v7.view.ContextThemeWrapper;
import android.support.v7.view.StandaloneActionMode;
import android.support.v7.view.SupportActionModeWrapper;
import android.support.v7.view.SupportMenuInflater;
import android.support.v7.view.WindowCallbackWrapper;
import android.support.v7.view.menu.ListMenuPresenter;
import android.support.v7.view.menu.MenuBuilder;
import android.support.v7.view.menu.MenuPresenter;
import android.support.v7.view.menu.MenuView;
import android.support.v7.widget.ActionBarContextView;
import android.support.v7.widget.AppCompatDrawableManager;
import android.support.v7.widget.ContentFrameLayout;
import android.support.v7.widget.DecorContentParent;
import android.support.v7.widget.FitWindowsViewGroup;
import android.support.v7.widget.TintTypedArray;
import android.support.v7.widget.Toolbar;
import android.support.v7.widget.VectorEnabledTintResources;
import android.support.v7.widget.ViewStubCompat;
import android.support.v7.widget.ViewUtils;
import android.text.TextUtils;
import android.util.AndroidRuntimeException;
import android.util.AttributeSet;
import android.util.DisplayMetrics;
import android.util.Log;
import android.util.TypedValue;
import android.view.ActionMode;
import android.view.KeyCharacterMap;
import android.view.KeyEvent;
import android.view.KeyboardShortcutGroup;
import android.view.LayoutInflater;
import android.view.Menu;
import android.view.MenuInflater;
import android.view.MenuItem;
import android.view.MotionEvent;
import android.view.View;
import android.view.ViewConfiguration;
import android.view.ViewGroup;
import android.view.ViewParent;
import android.view.Window;
import android.view.WindowManager;
import android.widget.FrameLayout;
import android.widget.PopupWindow;
import android.widget.TextView;
import java.util.List;
import org.xmlpull.v1.XmlPullParser;

class AppCompatDelegateImpl extends AppCompatDelegate implements MenuBuilder.Callback, LayoutInflater.Factory2 {
  private static final boolean DEBUG = false;
  
  static final String EXCEPTION_HANDLER_MESSAGE_SUFFIX = ". If the resource you are trying to use is a vector resource, you may be referencing it in an unsupported way. See AppCompatDelegate.setCompatVectorFromResourcesEnabled() for more info.";
  
  private static final boolean IS_PRE_LOLLIPOP;
  
  private static final String KEY_LOCAL_NIGHT_MODE = "appcompat:local_night_mode";
  
  private static boolean sInstalledExceptionHandler;
  
  private static final int[] sWindowBackgroundStyleable = new int[] { 16842836 };
  
  ActionBar mActionBar;
  
  private ActionMenuPresenterCallback mActionMenuPresenterCallback;
  
  ActionMode mActionMode;
  
  PopupWindow mActionModePopup;
  
  ActionBarContextView mActionModeView;
  
  final AppCompatCallback mAppCompatCallback;
  
  private AppCompatViewInflater mAppCompatViewInflater;
  
  final Window.Callback mAppCompatWindowCallback;
  
  private boolean mApplyDayNightCalled;
  
  private AutoNightModeManager mAutoNightModeManager;
  
  private boolean mClosingActionMenu;
  
  final Context mContext;
  
  private DecorContentParent mDecorContentParent;
  
  private boolean mEnableDefaultActionBarUp;
  
  ViewPropertyAnimatorCompat mFadeAnim = null;
  
  private boolean mFeatureIndeterminateProgress;
  
  private boolean mFeatureProgress;
  
  private boolean mHandleNativeActionModes = true;
  
  boolean mHasActionBar;
  
  int mInvalidatePanelMenuFeatures;
  
  boolean mInvalidatePanelMenuPosted;
  
  private final Runnable mInvalidatePanelMenuRunnable = new Runnable() {
      public void run() {
        if ((AppCompatDelegateImpl.this.mInvalidatePanelMenuFeatures & 0x1) != 0)
          AppCompatDelegateImpl.this.doInvalidatePanelMenu(0); 
        if ((AppCompatDelegateImpl.this.mInvalidatePanelMenuFeatures & 0x1000) != 0)
          AppCompatDelegateImpl.this.doInvalidatePanelMenu(108); 
        AppCompatDelegateImpl.this.mInvalidatePanelMenuPosted = false;
        AppCompatDelegateImpl.this.mInvalidatePanelMenuFeatures = 0;
      }
    };
  
  boolean mIsDestroyed;
  
  boolean mIsFloating;
  
  private int mLocalNightMode = -100;
  
  private boolean mLongPressBackDown;
  
  MenuInflater mMenuInflater;
  
  final Window.Callback mOriginalWindowCallback;
  
  boolean mOverlayActionBar;
  
  boolean mOverlayActionMode;
  
  private PanelMenuPresenterCallback mPanelMenuPresenterCallback;
  
  private PanelFeatureState[] mPanels;
  
  private PanelFeatureState mPreparedPanel;
  
  Runnable mShowActionModePopup;
  
  private View mStatusGuard;
  
  private ViewGroup mSubDecor;
  
  private boolean mSubDecorInstalled;
  
  private Rect mTempRect1;
  
  private Rect mTempRect2;
  
  private CharSequence mTitle;
  
  private TextView mTitleView;
  
  final Window mWindow;
  
  boolean mWindowNoTitle;
  
  static {
    if (bool && !sInstalledExceptionHandler) {
      Thread.setDefaultUncaughtExceptionHandler(new Thread.UncaughtExceptionHandler(Thread.getDefaultUncaughtExceptionHandler()) {
            private boolean shouldWrapException(Throwable param1Throwable) {
              boolean bool = param1Throwable instanceof Resources.NotFoundException;
              boolean bool1 = false;
              if (bool) {
                String str = param1Throwable.getMessage();
                if (str != null && (str.contains("drawable") || str.contains("Drawable")))
                  bool1 = true; 
                return bool1;
              } 
              return false;
            }
            
            public void uncaughtException(Thread param1Thread, Throwable param1Throwable) {
              if (shouldWrapException(param1Throwable)) {
                StringBuilder stringBuilder = new StringBuilder();
                stringBuilder.append(param1Throwable.getMessage());
                stringBuilder.append(". If the resource you are trying to use is a vector resource, you may be referencing it in an unsupported way. See AppCompatDelegate.setCompatVectorFromResourcesEnabled() for more info.");
                Resources.NotFoundException notFoundException = new Resources.NotFoundException(stringBuilder.toString());
                notFoundException.initCause(param1Throwable.getCause());
                notFoundException.setStackTrace(param1Throwable.getStackTrace());
                defHandler.uncaughtException(param1Thread, (Throwable)notFoundException);
              } else {
                defHandler.uncaughtException(param1Thread, param1Throwable);
              } 
            }
          });
      sInstalledExceptionHandler = true;
    } 
  }
  
  AppCompatDelegateImpl(Context paramContext, Window paramWindow, AppCompatCallback paramAppCompatCallback) {
    this.mContext = paramContext;
    this.mWindow = paramWindow;
    this.mAppCompatCallback = paramAppCompatCallback;
    Window.Callback callback = paramWindow.getCallback();
    this.mOriginalWindowCallback = callback;
    if (!(callback instanceof AppCompatWindowCallback)) {
      AppCompatWindowCallback appCompatWindowCallback = new AppCompatWindowCallback(this.mOriginalWindowCallback);
      this.mAppCompatWindowCallback = (Window.Callback)appCompatWindowCallback;
      this.mWindow.setCallback((Window.Callback)appCompatWindowCallback);
      TintTypedArray tintTypedArray = TintTypedArray.obtainStyledAttributes(paramContext, null, sWindowBackgroundStyleable);
      Drawable drawable = tintTypedArray.getDrawableIfKnown(0);
      if (drawable != null)
        this.mWindow.setBackgroundDrawable(drawable); 
      tintTypedArray.recycle();
      return;
    } 
    throw new IllegalStateException("AppCompat has already installed itself into the Window");
  }
  
  private void applyFixedSizeWindow() {
    ContentFrameLayout contentFrameLayout = (ContentFrameLayout)this.mSubDecor.findViewById(16908290);
    View view = this.mWindow.getDecorView();
    contentFrameLayout.setDecorPadding(view.getPaddingLeft(), view.getPaddingTop(), view.getPaddingRight(), view.getPaddingBottom());
    TypedArray typedArray = this.mContext.obtainStyledAttributes(R.styleable.AppCompatTheme);
    typedArray.getValue(R.styleable.AppCompatTheme_windowMinWidthMajor, contentFrameLayout.getMinWidthMajor());
    typedArray.getValue(R.styleable.AppCompatTheme_windowMinWidthMinor, contentFrameLayout.getMinWidthMinor());
    if (typedArray.hasValue(R.styleable.AppCompatTheme_windowFixedWidthMajor))
      typedArray.getValue(R.styleable.AppCompatTheme_windowFixedWidthMajor, contentFrameLayout.getFixedWidthMajor()); 
    if (typedArray.hasValue(R.styleable.AppCompatTheme_windowFixedWidthMinor))
      typedArray.getValue(R.styleable.AppCompatTheme_windowFixedWidthMinor, contentFrameLayout.getFixedWidthMinor()); 
    if (typedArray.hasValue(R.styleable.AppCompatTheme_windowFixedHeightMajor))
      typedArray.getValue(R.styleable.AppCompatTheme_windowFixedHeightMajor, contentFrameLayout.getFixedHeightMajor()); 
    if (typedArray.hasValue(R.styleable.AppCompatTheme_windowFixedHeightMinor))
      typedArray.getValue(R.styleable.AppCompatTheme_windowFixedHeightMinor, contentFrameLayout.getFixedHeightMinor()); 
    typedArray.recycle();
    contentFrameLayout.requestLayout();
  }
  
  private ViewGroup createSubDecor() {
    StringBuilder stringBuilder;
    TypedArray typedArray = this.mContext.obtainStyledAttributes(R.styleable.AppCompatTheme);
    if (typedArray.hasValue(R.styleable.AppCompatTheme_windowActionBar)) {
      ViewGroup viewGroup;
      DecorContentParent decorContentParent;
      if (typedArray.getBoolean(R.styleable.AppCompatTheme_windowNoTitle, false)) {
        requestWindowFeature(1);
      } else if (typedArray.getBoolean(R.styleable.AppCompatTheme_windowActionBar, false)) {
        requestWindowFeature(108);
      } 
      if (typedArray.getBoolean(R.styleable.AppCompatTheme_windowActionBarOverlay, false))
        requestWindowFeature(109); 
      if (typedArray.getBoolean(R.styleable.AppCompatTheme_windowActionModeOverlay, false))
        requestWindowFeature(10); 
      this.mIsFloating = typedArray.getBoolean(R.styleable.AppCompatTheme_android_windowIsFloating, false);
      typedArray.recycle();
      this.mWindow.getDecorView();
      LayoutInflater layoutInflater = LayoutInflater.from(this.mContext);
      typedArray = null;
      if (!this.mWindowNoTitle) {
        if (this.mIsFloating) {
          viewGroup = (ViewGroup)layoutInflater.inflate(R.layout.abc_dialog_title_material, null);
          this.mOverlayActionBar = false;
          this.mHasActionBar = false;
        } else if (this.mHasActionBar) {
          Context context;
          TypedValue typedValue = new TypedValue();
          this.mContext.getTheme().resolveAttribute(R.attr.actionBarTheme, typedValue, true);
          if (typedValue.resourceId != 0) {
            ContextThemeWrapper contextThemeWrapper = new ContextThemeWrapper(this.mContext, typedValue.resourceId);
          } else {
            context = this.mContext;
          } 
          viewGroup = (ViewGroup)LayoutInflater.from(context).inflate(R.layout.abc_screen_toolbar, null);
          decorContentParent = (DecorContentParent)viewGroup.findViewById(R.id.decor_content_parent);
          this.mDecorContentParent = decorContentParent;
          decorContentParent.setWindowCallback(getWindowCallback());
          if (this.mOverlayActionBar)
            this.mDecorContentParent.initFeature(109); 
          if (this.mFeatureProgress)
            this.mDecorContentParent.initFeature(2); 
          if (this.mFeatureIndeterminateProgress)
            this.mDecorContentParent.initFeature(5); 
        } 
      } else {
        if (this.mOverlayActionMode) {
          viewGroup = (ViewGroup)decorContentParent.inflate(R.layout.abc_screen_simple_overlay_action_mode, null);
        } else {
          viewGroup = (ViewGroup)decorContentParent.inflate(R.layout.abc_screen_simple, null);
        } 
        if (Build.VERSION.SDK_INT >= 21) {
          ViewCompat.setOnApplyWindowInsetsListener((View)viewGroup, new OnApplyWindowInsetsListener() {
                public WindowInsetsCompat onApplyWindowInsets(View param1View, WindowInsetsCompat param1WindowInsetsCompat) {
                  int i = param1WindowInsetsCompat.getSystemWindowInsetTop();
                  int j = AppCompatDelegateImpl.this.updateStatusGuard(i);
                  WindowInsetsCompat windowInsetsCompat = param1WindowInsetsCompat;
                  if (i != j)
                    windowInsetsCompat = param1WindowInsetsCompat.replaceSystemWindowInsets(param1WindowInsetsCompat.getSystemWindowInsetLeft(), j, param1WindowInsetsCompat.getSystemWindowInsetRight(), param1WindowInsetsCompat.getSystemWindowInsetBottom()); 
                  return ViewCompat.onApplyWindowInsets(param1View, windowInsetsCompat);
                }
              });
        } else {
          ((FitWindowsViewGroup)viewGroup).setOnFitSystemWindowsListener(new FitWindowsViewGroup.OnFitSystemWindowsListener() {
                public void onFitSystemWindows(Rect param1Rect) {
                  param1Rect.top = AppCompatDelegateImpl.this.updateStatusGuard(param1Rect.top);
                }
              });
        } 
      } 
      if (viewGroup != null) {
        if (this.mDecorContentParent == null)
          this.mTitleView = (TextView)viewGroup.findViewById(R.id.title); 
        ViewUtils.makeOptionalFitsSystemWindows((View)viewGroup);
        ContentFrameLayout contentFrameLayout = (ContentFrameLayout)viewGroup.findViewById(R.id.action_bar_activity_content);
        ViewGroup viewGroup1 = (ViewGroup)this.mWindow.findViewById(16908290);
        if (viewGroup1 != null) {
          while (viewGroup1.getChildCount() > 0) {
            View view = viewGroup1.getChildAt(0);
            viewGroup1.removeViewAt(0);
            contentFrameLayout.addView(view);
          } 
          viewGroup1.setId(-1);
          contentFrameLayout.setId(16908290);
          if (viewGroup1 instanceof FrameLayout)
            ((FrameLayout)viewGroup1).setForeground(null); 
        } 
        this.mWindow.setContentView((View)viewGroup);
        contentFrameLayout.setAttachListener(new ContentFrameLayout.OnAttachListener() {
              public void onAttachedFromWindow() {}
              
              public void onDetachedFromWindow() {
                AppCompatDelegateImpl.this.dismissPopups();
              }
            });
        return viewGroup;
      } 
      stringBuilder = new StringBuilder();
      stringBuilder.append("AppCompat does not support the current theme features: { windowActionBar: ");
      stringBuilder.append(this.mHasActionBar);
      stringBuilder.append(", windowActionBarOverlay: ");
      stringBuilder.append(this.mOverlayActionBar);
      stringBuilder.append(", android:windowIsFloating: ");
      stringBuilder.append(this.mIsFloating);
      stringBuilder.append(", windowActionModeOverlay: ");
      stringBuilder.append(this.mOverlayActionMode);
      stringBuilder.append(", windowNoTitle: ");
      stringBuilder.append(this.mWindowNoTitle);
      stringBuilder.append(" }");
      throw new IllegalArgumentException(stringBuilder.toString());
    } 
    stringBuilder.recycle();
    throw new IllegalStateException("You need to use a Theme.AppCompat theme (or descendant) with this activity.");
  }
  
  private void ensureAutoNightModeManager() {
    if (this.mAutoNightModeManager == null)
      this.mAutoNightModeManager = new AutoNightModeManager(TwilightManager.getInstance(this.mContext)); 
  }
  
  private void ensureSubDecor() {
    if (!this.mSubDecorInstalled) {
      this.mSubDecor = createSubDecor();
      CharSequence charSequence = getTitle();
      if (!TextUtils.isEmpty(charSequence)) {
        DecorContentParent decorContentParent = this.mDecorContentParent;
        if (decorContentParent != null) {
          decorContentParent.setWindowTitle(charSequence);
        } else if (peekSupportActionBar() != null) {
          peekSupportActionBar().setWindowTitle(charSequence);
        } else {
          TextView textView = this.mTitleView;
          if (textView != null)
            textView.setText(charSequence); 
        } 
      } 
      applyFixedSizeWindow();
      onSubDecorInstalled(this.mSubDecor);
      this.mSubDecorInstalled = true;
      PanelFeatureState panelFeatureState = getPanelState(0, false);
      if (!this.mIsDestroyed && (panelFeatureState == null || panelFeatureState.menu == null))
        invalidatePanelMenu(108); 
    } 
  }
  
  private int getNightMode() {
    int i = this.mLocalNightMode;
    if (i == -100)
      i = getDefaultNightMode(); 
    return i;
  }
  
  private void initWindowDecorActionBar() {
    ensureSubDecor();
    if (!this.mHasActionBar || this.mActionBar != null)
      return; 
    Window.Callback callback = this.mOriginalWindowCallback;
    if (callback instanceof Activity) {
      this.mActionBar = new WindowDecorActionBar((Activity)this.mOriginalWindowCallback, this.mOverlayActionBar);
    } else if (callback instanceof Dialog) {
      this.mActionBar = new WindowDecorActionBar((Dialog)this.mOriginalWindowCallback);
    } 
    ActionBar actionBar = this.mActionBar;
    if (actionBar != null)
      actionBar.setDefaultDisplayHomeAsUpEnabled(this.mEnableDefaultActionBarUp); 
  }
  
  private boolean initializePanelContent(PanelFeatureState paramPanelFeatureState) {
    View view = paramPanelFeatureState.createdPanelView;
    boolean bool = true;
    if (view != null) {
      paramPanelFeatureState.shownPanelView = paramPanelFeatureState.createdPanelView;
      return true;
    } 
    if (paramPanelFeatureState.menu == null)
      return false; 
    if (this.mPanelMenuPresenterCallback == null)
      this.mPanelMenuPresenterCallback = new PanelMenuPresenterCallback(); 
    paramPanelFeatureState.shownPanelView = (View)paramPanelFeatureState.getListMenuView(this.mPanelMenuPresenterCallback);
    if (paramPanelFeatureState.shownPanelView == null)
      bool = false; 
    return bool;
  }
  
  private boolean initializePanelDecor(PanelFeatureState paramPanelFeatureState) {
    paramPanelFeatureState.setStyle(getActionBarThemedContext());
    paramPanelFeatureState.decorView = (ViewGroup)new ListMenuDecorView(paramPanelFeatureState.listPresenterContext);
    paramPanelFeatureState.gravity = 81;
    return true;
  }
  
  private boolean initializePanelMenu(PanelFeatureState paramPanelFeatureState) {
    // Byte code:
    //   0: aload_0
    //   1: getfield mContext : Landroid/content/Context;
    //   4: astore_2
    //   5: aload_1
    //   6: getfield featureId : I
    //   9: ifeq -> 23
    //   12: aload_2
    //   13: astore_3
    //   14: aload_1
    //   15: getfield featureId : I
    //   18: bipush #108
    //   20: if_icmpne -> 190
    //   23: aload_2
    //   24: astore_3
    //   25: aload_0
    //   26: getfield mDecorContentParent : Landroid/support/v7/widget/DecorContentParent;
    //   29: ifnull -> 190
    //   32: new android/util/TypedValue
    //   35: dup
    //   36: invokespecial <init> : ()V
    //   39: astore #4
    //   41: aload_2
    //   42: invokevirtual getTheme : ()Landroid/content/res/Resources$Theme;
    //   45: astore #5
    //   47: aload #5
    //   49: getstatic android/support/v7/appcompat/R$attr.actionBarTheme : I
    //   52: aload #4
    //   54: iconst_1
    //   55: invokevirtual resolveAttribute : (ILandroid/util/TypedValue;Z)Z
    //   58: pop
    //   59: aconst_null
    //   60: astore_3
    //   61: aload #4
    //   63: getfield resourceId : I
    //   66: ifeq -> 107
    //   69: aload_2
    //   70: invokevirtual getResources : ()Landroid/content/res/Resources;
    //   73: invokevirtual newTheme : ()Landroid/content/res/Resources$Theme;
    //   76: astore_3
    //   77: aload_3
    //   78: aload #5
    //   80: invokevirtual setTo : (Landroid/content/res/Resources$Theme;)V
    //   83: aload_3
    //   84: aload #4
    //   86: getfield resourceId : I
    //   89: iconst_1
    //   90: invokevirtual applyStyle : (IZ)V
    //   93: aload_3
    //   94: getstatic android/support/v7/appcompat/R$attr.actionBarWidgetTheme : I
    //   97: aload #4
    //   99: iconst_1
    //   100: invokevirtual resolveAttribute : (ILandroid/util/TypedValue;Z)Z
    //   103: pop
    //   104: goto -> 119
    //   107: aload #5
    //   109: getstatic android/support/v7/appcompat/R$attr.actionBarWidgetTheme : I
    //   112: aload #4
    //   114: iconst_1
    //   115: invokevirtual resolveAttribute : (ILandroid/util/TypedValue;Z)Z
    //   118: pop
    //   119: aload_3
    //   120: astore #6
    //   122: aload #4
    //   124: getfield resourceId : I
    //   127: ifeq -> 164
    //   130: aload_3
    //   131: astore #6
    //   133: aload_3
    //   134: ifnonnull -> 153
    //   137: aload_2
    //   138: invokevirtual getResources : ()Landroid/content/res/Resources;
    //   141: invokevirtual newTheme : ()Landroid/content/res/Resources$Theme;
    //   144: astore #6
    //   146: aload #6
    //   148: aload #5
    //   150: invokevirtual setTo : (Landroid/content/res/Resources$Theme;)V
    //   153: aload #6
    //   155: aload #4
    //   157: getfield resourceId : I
    //   160: iconst_1
    //   161: invokevirtual applyStyle : (IZ)V
    //   164: aload_2
    //   165: astore_3
    //   166: aload #6
    //   168: ifnull -> 190
    //   171: new android/support/v7/view/ContextThemeWrapper
    //   174: dup
    //   175: aload_2
    //   176: iconst_0
    //   177: invokespecial <init> : (Landroid/content/Context;I)V
    //   180: astore_3
    //   181: aload_3
    //   182: invokevirtual getTheme : ()Landroid/content/res/Resources$Theme;
    //   185: aload #6
    //   187: invokevirtual setTo : (Landroid/content/res/Resources$Theme;)V
    //   190: new android/support/v7/view/menu/MenuBuilder
    //   193: dup
    //   194: aload_3
    //   195: invokespecial <init> : (Landroid/content/Context;)V
    //   198: astore_3
    //   199: aload_3
    //   200: aload_0
    //   201: invokevirtual setCallback : (Landroid/support/v7/view/menu/MenuBuilder$Callback;)V
    //   204: aload_1
    //   205: aload_3
    //   206: invokevirtual setMenu : (Landroid/support/v7/view/menu/MenuBuilder;)V
    //   209: iconst_1
    //   210: ireturn
  }
  
  private void invalidatePanelMenu(int paramInt) {
    this.mInvalidatePanelMenuFeatures |= 1 << paramInt;
    if (!this.mInvalidatePanelMenuPosted) {
      ViewCompat.postOnAnimation(this.mWindow.getDecorView(), this.mInvalidatePanelMenuRunnable);
      this.mInvalidatePanelMenuPosted = true;
    } 
  }
  
  private boolean onKeyDownPanel(int paramInt, KeyEvent paramKeyEvent) {
    if (paramKeyEvent.getRepeatCount() == 0) {
      PanelFeatureState panelFeatureState = getPanelState(paramInt, true);
      if (!panelFeatureState.isOpen)
        return preparePanel(panelFeatureState, paramKeyEvent); 
    } 
    return false;
  }
  
  private boolean onKeyUpPanel(int paramInt, KeyEvent paramKeyEvent) {
    // Byte code:
    //   0: aload_0
    //   1: getfield mActionMode : Landroid/support/v7/view/ActionMode;
    //   4: ifnull -> 9
    //   7: iconst_0
    //   8: ireturn
    //   9: iconst_0
    //   10: istore_3
    //   11: aload_0
    //   12: iload_1
    //   13: iconst_1
    //   14: invokevirtual getPanelState : (IZ)Landroid/support/v7/app/AppCompatDelegateImpl$PanelFeatureState;
    //   17: astore #4
    //   19: iload_1
    //   20: ifne -> 120
    //   23: aload_0
    //   24: getfield mDecorContentParent : Landroid/support/v7/widget/DecorContentParent;
    //   27: astore #5
    //   29: aload #5
    //   31: ifnull -> 120
    //   34: aload #5
    //   36: invokeinterface canShowOverflowMenu : ()Z
    //   41: ifeq -> 120
    //   44: aload_0
    //   45: getfield mContext : Landroid/content/Context;
    //   48: invokestatic get : (Landroid/content/Context;)Landroid/view/ViewConfiguration;
    //   51: invokevirtual hasPermanentMenuKey : ()Z
    //   54: ifne -> 120
    //   57: aload_0
    //   58: getfield mDecorContentParent : Landroid/support/v7/widget/DecorContentParent;
    //   61: invokeinterface isOverflowMenuShowing : ()Z
    //   66: ifne -> 106
    //   69: iload_3
    //   70: istore #6
    //   72: aload_0
    //   73: getfield mIsDestroyed : Z
    //   76: ifne -> 211
    //   79: iload_3
    //   80: istore #6
    //   82: aload_0
    //   83: aload #4
    //   85: aload_2
    //   86: invokespecial preparePanel : (Landroid/support/v7/app/AppCompatDelegateImpl$PanelFeatureState;Landroid/view/KeyEvent;)Z
    //   89: ifeq -> 211
    //   92: aload_0
    //   93: getfield mDecorContentParent : Landroid/support/v7/widget/DecorContentParent;
    //   96: invokeinterface showOverflowMenu : ()Z
    //   101: istore #6
    //   103: goto -> 211
    //   106: aload_0
    //   107: getfield mDecorContentParent : Landroid/support/v7/widget/DecorContentParent;
    //   110: invokeinterface hideOverflowMenu : ()Z
    //   115: istore #6
    //   117: goto -> 211
    //   120: aload #4
    //   122: getfield isOpen : Z
    //   125: ifne -> 197
    //   128: aload #4
    //   130: getfield isHandled : Z
    //   133: ifeq -> 139
    //   136: goto -> 197
    //   139: iload_3
    //   140: istore #6
    //   142: aload #4
    //   144: getfield isPrepared : Z
    //   147: ifeq -> 211
    //   150: iconst_1
    //   151: istore #7
    //   153: aload #4
    //   155: getfield refreshMenuContent : Z
    //   158: ifeq -> 176
    //   161: aload #4
    //   163: iconst_0
    //   164: putfield isPrepared : Z
    //   167: aload_0
    //   168: aload #4
    //   170: aload_2
    //   171: invokespecial preparePanel : (Landroid/support/v7/app/AppCompatDelegateImpl$PanelFeatureState;Landroid/view/KeyEvent;)Z
    //   174: istore #7
    //   176: iload_3
    //   177: istore #6
    //   179: iload #7
    //   181: ifeq -> 211
    //   184: aload_0
    //   185: aload #4
    //   187: aload_2
    //   188: invokespecial openPanel : (Landroid/support/v7/app/AppCompatDelegateImpl$PanelFeatureState;Landroid/view/KeyEvent;)V
    //   191: iconst_1
    //   192: istore #6
    //   194: goto -> 211
    //   197: aload #4
    //   199: getfield isOpen : Z
    //   202: istore #6
    //   204: aload_0
    //   205: aload #4
    //   207: iconst_1
    //   208: invokevirtual closePanel : (Landroid/support/v7/app/AppCompatDelegateImpl$PanelFeatureState;Z)V
    //   211: iload #6
    //   213: ifeq -> 252
    //   216: aload_0
    //   217: getfield mContext : Landroid/content/Context;
    //   220: ldc_w 'audio'
    //   223: invokevirtual getSystemService : (Ljava/lang/String;)Ljava/lang/Object;
    //   226: checkcast android/media/AudioManager
    //   229: astore_2
    //   230: aload_2
    //   231: ifnull -> 242
    //   234: aload_2
    //   235: iconst_0
    //   236: invokevirtual playSoundEffect : (I)V
    //   239: goto -> 252
    //   242: ldc_w 'AppCompatDelegate'
    //   245: ldc_w 'Couldn't get audio manager'
    //   248: invokestatic w : (Ljava/lang/String;Ljava/lang/String;)I
    //   251: pop
    //   252: iload #6
    //   254: ireturn
  }
  
  private void openPanel(PanelFeatureState paramPanelFeatureState, KeyEvent paramKeyEvent) {
    // Byte code:
    //   0: aload_1
    //   1: getfield isOpen : Z
    //   4: ifne -> 429
    //   7: aload_0
    //   8: getfield mIsDestroyed : Z
    //   11: ifeq -> 17
    //   14: goto -> 429
    //   17: aload_1
    //   18: getfield featureId : I
    //   21: ifne -> 56
    //   24: aload_0
    //   25: getfield mContext : Landroid/content/Context;
    //   28: invokevirtual getResources : ()Landroid/content/res/Resources;
    //   31: invokevirtual getConfiguration : ()Landroid/content/res/Configuration;
    //   34: getfield screenLayout : I
    //   37: bipush #15
    //   39: iand
    //   40: iconst_4
    //   41: if_icmpne -> 49
    //   44: iconst_1
    //   45: istore_3
    //   46: goto -> 51
    //   49: iconst_0
    //   50: istore_3
    //   51: iload_3
    //   52: ifeq -> 56
    //   55: return
    //   56: aload_0
    //   57: invokevirtual getWindowCallback : ()Landroid/view/Window$Callback;
    //   60: astore #4
    //   62: aload #4
    //   64: ifnull -> 92
    //   67: aload #4
    //   69: aload_1
    //   70: getfield featureId : I
    //   73: aload_1
    //   74: getfield menu : Landroid/support/v7/view/menu/MenuBuilder;
    //   77: invokeinterface onMenuOpened : (ILandroid/view/Menu;)Z
    //   82: ifne -> 92
    //   85: aload_0
    //   86: aload_1
    //   87: iconst_1
    //   88: invokevirtual closePanel : (Landroid/support/v7/app/AppCompatDelegateImpl$PanelFeatureState;Z)V
    //   91: return
    //   92: aload_0
    //   93: getfield mContext : Landroid/content/Context;
    //   96: ldc_w 'window'
    //   99: invokevirtual getSystemService : (Ljava/lang/String;)Ljava/lang/Object;
    //   102: checkcast android/view/WindowManager
    //   105: astore #5
    //   107: aload #5
    //   109: ifnonnull -> 113
    //   112: return
    //   113: aload_0
    //   114: aload_1
    //   115: aload_2
    //   116: invokespecial preparePanel : (Landroid/support/v7/app/AppCompatDelegateImpl$PanelFeatureState;Landroid/view/KeyEvent;)Z
    //   119: ifne -> 123
    //   122: return
    //   123: bipush #-2
    //   125: istore #6
    //   127: aload_1
    //   128: getfield decorView : Landroid/view/ViewGroup;
    //   131: ifnull -> 188
    //   134: aload_1
    //   135: getfield refreshDecorView : Z
    //   138: ifeq -> 144
    //   141: goto -> 188
    //   144: aload_1
    //   145: getfield createdPanelView : Landroid/view/View;
    //   148: ifnull -> 182
    //   151: aload_1
    //   152: getfield createdPanelView : Landroid/view/View;
    //   155: invokevirtual getLayoutParams : ()Landroid/view/ViewGroup$LayoutParams;
    //   158: astore_2
    //   159: iload #6
    //   161: istore_3
    //   162: aload_2
    //   163: ifnull -> 362
    //   166: iload #6
    //   168: istore_3
    //   169: aload_2
    //   170: getfield width : I
    //   173: iconst_m1
    //   174: if_icmpne -> 362
    //   177: iconst_m1
    //   178: istore_3
    //   179: goto -> 362
    //   182: iload #6
    //   184: istore_3
    //   185: goto -> 362
    //   188: aload_1
    //   189: getfield decorView : Landroid/view/ViewGroup;
    //   192: ifnonnull -> 211
    //   195: aload_0
    //   196: aload_1
    //   197: invokespecial initializePanelDecor : (Landroid/support/v7/app/AppCompatDelegateImpl$PanelFeatureState;)Z
    //   200: ifeq -> 210
    //   203: aload_1
    //   204: getfield decorView : Landroid/view/ViewGroup;
    //   207: ifnonnull -> 235
    //   210: return
    //   211: aload_1
    //   212: getfield refreshDecorView : Z
    //   215: ifeq -> 235
    //   218: aload_1
    //   219: getfield decorView : Landroid/view/ViewGroup;
    //   222: invokevirtual getChildCount : ()I
    //   225: ifle -> 235
    //   228: aload_1
    //   229: getfield decorView : Landroid/view/ViewGroup;
    //   232: invokevirtual removeAllViews : ()V
    //   235: aload_0
    //   236: aload_1
    //   237: invokespecial initializePanelContent : (Landroid/support/v7/app/AppCompatDelegateImpl$PanelFeatureState;)Z
    //   240: ifeq -> 428
    //   243: aload_1
    //   244: invokevirtual hasPanelItems : ()Z
    //   247: ifne -> 253
    //   250: goto -> 428
    //   253: aload_1
    //   254: getfield shownPanelView : Landroid/view/View;
    //   257: invokevirtual getLayoutParams : ()Landroid/view/ViewGroup$LayoutParams;
    //   260: astore #4
    //   262: aload #4
    //   264: astore_2
    //   265: aload #4
    //   267: ifnonnull -> 282
    //   270: new android/view/ViewGroup$LayoutParams
    //   273: dup
    //   274: bipush #-2
    //   276: bipush #-2
    //   278: invokespecial <init> : (II)V
    //   281: astore_2
    //   282: aload_1
    //   283: getfield background : I
    //   286: istore_3
    //   287: aload_1
    //   288: getfield decorView : Landroid/view/ViewGroup;
    //   291: iload_3
    //   292: invokevirtual setBackgroundResource : (I)V
    //   295: aload_1
    //   296: getfield shownPanelView : Landroid/view/View;
    //   299: invokevirtual getParent : ()Landroid/view/ViewParent;
    //   302: astore #4
    //   304: aload #4
    //   306: ifnull -> 329
    //   309: aload #4
    //   311: instanceof android/view/ViewGroup
    //   314: ifeq -> 329
    //   317: aload #4
    //   319: checkcast android/view/ViewGroup
    //   322: aload_1
    //   323: getfield shownPanelView : Landroid/view/View;
    //   326: invokevirtual removeView : (Landroid/view/View;)V
    //   329: aload_1
    //   330: getfield decorView : Landroid/view/ViewGroup;
    //   333: aload_1
    //   334: getfield shownPanelView : Landroid/view/View;
    //   337: aload_2
    //   338: invokevirtual addView : (Landroid/view/View;Landroid/view/ViewGroup$LayoutParams;)V
    //   341: aload_1
    //   342: getfield shownPanelView : Landroid/view/View;
    //   345: invokevirtual hasFocus : ()Z
    //   348: ifne -> 182
    //   351: aload_1
    //   352: getfield shownPanelView : Landroid/view/View;
    //   355: invokevirtual requestFocus : ()Z
    //   358: pop
    //   359: goto -> 182
    //   362: aload_1
    //   363: iconst_0
    //   364: putfield isHandled : Z
    //   367: new android/view/WindowManager$LayoutParams
    //   370: dup
    //   371: iload_3
    //   372: bipush #-2
    //   374: aload_1
    //   375: getfield x : I
    //   378: aload_1
    //   379: getfield y : I
    //   382: sipush #1002
    //   385: ldc_w 8519680
    //   388: bipush #-3
    //   390: invokespecial <init> : (IIIIIII)V
    //   393: astore_2
    //   394: aload_2
    //   395: aload_1
    //   396: getfield gravity : I
    //   399: putfield gravity : I
    //   402: aload_2
    //   403: aload_1
    //   404: getfield windowAnimations : I
    //   407: putfield windowAnimations : I
    //   410: aload #5
    //   412: aload_1
    //   413: getfield decorView : Landroid/view/ViewGroup;
    //   416: aload_2
    //   417: invokeinterface addView : (Landroid/view/View;Landroid/view/ViewGroup$LayoutParams;)V
    //   422: aload_1
    //   423: iconst_1
    //   424: putfield isOpen : Z
    //   427: return
    //   428: return
    //   429: return
  }
  
  private boolean performPanelShortcut(PanelFeatureState paramPanelFeatureState, int paramInt1, KeyEvent paramKeyEvent, int paramInt2) {
    // Byte code:
    //   0: aload_3
    //   1: invokevirtual isSystem : ()Z
    //   4: ifeq -> 9
    //   7: iconst_0
    //   8: ireturn
    //   9: iconst_0
    //   10: istore #5
    //   12: aload_1
    //   13: getfield isPrepared : Z
    //   16: ifne -> 32
    //   19: iload #5
    //   21: istore #6
    //   23: aload_0
    //   24: aload_1
    //   25: aload_3
    //   26: invokespecial preparePanel : (Landroid/support/v7/app/AppCompatDelegateImpl$PanelFeatureState;Landroid/view/KeyEvent;)Z
    //   29: ifeq -> 56
    //   32: iload #5
    //   34: istore #6
    //   36: aload_1
    //   37: getfield menu : Landroid/support/v7/view/menu/MenuBuilder;
    //   40: ifnull -> 56
    //   43: aload_1
    //   44: getfield menu : Landroid/support/v7/view/menu/MenuBuilder;
    //   47: iload_2
    //   48: aload_3
    //   49: iload #4
    //   51: invokevirtual performShortcut : (ILandroid/view/KeyEvent;I)Z
    //   54: istore #6
    //   56: iload #6
    //   58: ifeq -> 81
    //   61: iload #4
    //   63: iconst_1
    //   64: iand
    //   65: ifne -> 81
    //   68: aload_0
    //   69: getfield mDecorContentParent : Landroid/support/v7/widget/DecorContentParent;
    //   72: ifnonnull -> 81
    //   75: aload_0
    //   76: aload_1
    //   77: iconst_1
    //   78: invokevirtual closePanel : (Landroid/support/v7/app/AppCompatDelegateImpl$PanelFeatureState;Z)V
    //   81: iload #6
    //   83: ireturn
  }
  
  private boolean preparePanel(PanelFeatureState paramPanelFeatureState, KeyEvent paramKeyEvent) {
    DecorContentParent decorContentParent;
    int i;
    if (this.mIsDestroyed)
      return false; 
    if (paramPanelFeatureState.isPrepared)
      return true; 
    PanelFeatureState panelFeatureState = this.mPreparedPanel;
    if (panelFeatureState != null && panelFeatureState != paramPanelFeatureState)
      closePanel(panelFeatureState, false); 
    Window.Callback callback = getWindowCallback();
    if (callback != null)
      paramPanelFeatureState.createdPanelView = callback.onCreatePanelView(paramPanelFeatureState.featureId); 
    if (paramPanelFeatureState.featureId == 0 || paramPanelFeatureState.featureId == 108) {
      i = 1;
    } else {
      i = 0;
    } 
    if (i) {
      DecorContentParent decorContentParent1 = this.mDecorContentParent;
      if (decorContentParent1 != null)
        decorContentParent1.setMenuPrepared(); 
    } 
    if (paramPanelFeatureState.createdPanelView == null && (!i || !(peekSupportActionBar() instanceof ToolbarActionBar))) {
      DecorContentParent decorContentParent1;
      boolean bool;
      if (paramPanelFeatureState.menu == null || paramPanelFeatureState.refreshMenuContent) {
        if (paramPanelFeatureState.menu == null && (!initializePanelMenu(paramPanelFeatureState) || paramPanelFeatureState.menu == null))
          return false; 
        if (i && this.mDecorContentParent != null) {
          if (this.mActionMenuPresenterCallback == null)
            this.mActionMenuPresenterCallback = new ActionMenuPresenterCallback(); 
          this.mDecorContentParent.setMenu((Menu)paramPanelFeatureState.menu, this.mActionMenuPresenterCallback);
        } 
        paramPanelFeatureState.menu.stopDispatchingItemsChanged();
        if (!callback.onCreatePanelMenu(paramPanelFeatureState.featureId, (Menu)paramPanelFeatureState.menu)) {
          paramPanelFeatureState.setMenu(null);
          if (i) {
            decorContentParent = this.mDecorContentParent;
            if (decorContentParent != null)
              decorContentParent.setMenu(null, this.mActionMenuPresenterCallback); 
          } 
          return false;
        } 
        ((PanelFeatureState)decorContentParent).refreshMenuContent = false;
      } 
      ((PanelFeatureState)decorContentParent).menu.stopDispatchingItemsChanged();
      if (((PanelFeatureState)decorContentParent).frozenActionViewState != null) {
        ((PanelFeatureState)decorContentParent).menu.restoreActionViewStates(((PanelFeatureState)decorContentParent).frozenActionViewState);
        ((PanelFeatureState)decorContentParent).frozenActionViewState = null;
      } 
      if (!callback.onPreparePanel(0, ((PanelFeatureState)decorContentParent).createdPanelView, (Menu)((PanelFeatureState)decorContentParent).menu)) {
        if (i) {
          decorContentParent1 = this.mDecorContentParent;
          if (decorContentParent1 != null)
            decorContentParent1.setMenu(null, this.mActionMenuPresenterCallback); 
        } 
        ((PanelFeatureState)decorContentParent).menu.startDispatchingItemsChanged();
        return false;
      } 
      if (decorContentParent1 != null) {
        i = decorContentParent1.getDeviceId();
      } else {
        i = -1;
      } 
      if (KeyCharacterMap.load(i).getKeyboardType() != 1) {
        bool = true;
      } else {
        bool = false;
      } 
      ((PanelFeatureState)decorContentParent).qwertyMode = bool;
      ((PanelFeatureState)decorContentParent).menu.setQwertyMode(((PanelFeatureState)decorContentParent).qwertyMode);
      ((PanelFeatureState)decorContentParent).menu.startDispatchingItemsChanged();
    } 
    ((PanelFeatureState)decorContentParent).isPrepared = true;
    ((PanelFeatureState)decorContentParent).isHandled = false;
    this.mPreparedPanel = (PanelFeatureState)decorContentParent;
    return true;
  }
  
  private void reopenMenu(MenuBuilder paramMenuBuilder, boolean paramBoolean) {
    DecorContentParent decorContentParent = this.mDecorContentParent;
    if (decorContentParent != null && decorContentParent.canShowOverflowMenu() && (!ViewConfiguration.get(this.mContext).hasPermanentMenuKey() || this.mDecorContentParent.isOverflowMenuShowPending())) {
      Window.Callback callback = getWindowCallback();
      if (!this.mDecorContentParent.isOverflowMenuShowing() || !paramBoolean) {
        if (callback != null && !this.mIsDestroyed) {
          if (this.mInvalidatePanelMenuPosted && (this.mInvalidatePanelMenuFeatures & 0x1) != 0) {
            this.mWindow.getDecorView().removeCallbacks(this.mInvalidatePanelMenuRunnable);
            this.mInvalidatePanelMenuRunnable.run();
          } 
          PanelFeatureState panelFeatureState1 = getPanelState(0, true);
          if (panelFeatureState1.menu != null && !panelFeatureState1.refreshMenuContent && callback.onPreparePanel(0, panelFeatureState1.createdPanelView, (Menu)panelFeatureState1.menu)) {
            callback.onMenuOpened(108, (Menu)panelFeatureState1.menu);
            this.mDecorContentParent.showOverflowMenu();
          } 
        } 
        return;
      } 
      this.mDecorContentParent.hideOverflowMenu();
      if (!this.mIsDestroyed)
        callback.onPanelClosed(108, (Menu)(getPanelState(0, true)).menu); 
      return;
    } 
    PanelFeatureState panelFeatureState = getPanelState(0, true);
    panelFeatureState.refreshDecorView = true;
    closePanel(panelFeatureState, false);
    openPanel(panelFeatureState, null);
  }
  
  private int sanitizeWindowFeatureId(int paramInt) {
    if (paramInt == 8) {
      Log.i("AppCompatDelegate", "You should now use the AppCompatDelegate.FEATURE_SUPPORT_ACTION_BAR id when requesting this feature.");
      return 108;
    } 
    if (paramInt == 9) {
      Log.i("AppCompatDelegate", "You should now use the AppCompatDelegate.FEATURE_SUPPORT_ACTION_BAR_OVERLAY id when requesting this feature.");
      return 109;
    } 
    return paramInt;
  }
  
  private boolean shouldInheritContext(ViewParent paramViewParent) {
    if (paramViewParent == null)
      return false; 
    View view = this.mWindow.getDecorView();
    while (true) {
      if (paramViewParent == null)
        return true; 
      if (paramViewParent == view || !(paramViewParent instanceof View) || ViewCompat.isAttachedToWindow((View)paramViewParent))
        break; 
      paramViewParent = paramViewParent.getParent();
    } 
    return false;
  }
  
  private boolean shouldRecreateOnNightModeChange() {
    boolean bool = this.mApplyDayNightCalled;
    boolean bool1 = false;
    if (bool) {
      Context context = this.mContext;
      if (context instanceof Activity) {
        PackageManager packageManager = context.getPackageManager();
        try {
          ComponentName componentName = new ComponentName();
          this(this.mContext, this.mContext.getClass());
          int i = (packageManager.getActivityInfo(componentName, 0)).configChanges;
          if ((i & 0x200) == 0)
            bool1 = true; 
          return bool1;
        } catch (android.content.pm.PackageManager.NameNotFoundException nameNotFoundException) {
          Log.d("AppCompatDelegate", "Exception while getting ActivityInfo", (Throwable)nameNotFoundException);
          return true;
        } 
      } 
    } 
    return false;
  }
  
  private void throwFeatureRequestIfSubDecorInstalled() {
    if (!this.mSubDecorInstalled)
      return; 
    throw new AndroidRuntimeException("Window feature must be requested before adding content");
  }
  
  private boolean updateForNightMode(int paramInt) {
    Resources resources = this.mContext.getResources();
    Configuration configuration = resources.getConfiguration();
    int i = configuration.uiMode;
    if (paramInt == 2) {
      paramInt = 32;
    } else {
      paramInt = 16;
    } 
    if ((i & 0x30) != paramInt) {
      if (shouldRecreateOnNightModeChange()) {
        ((Activity)this.mContext).recreate();
      } else {
        configuration = new Configuration(configuration);
        DisplayMetrics displayMetrics = resources.getDisplayMetrics();
        configuration.uiMode = configuration.uiMode & 0xFFFFFFCF | paramInt;
        resources.updateConfiguration(configuration, displayMetrics);
        if (Build.VERSION.SDK_INT < 26)
          ResourcesFlusher.flush(resources); 
      } 
      return true;
    } 
    return false;
  }
  
  public void addContentView(View paramView, ViewGroup.LayoutParams paramLayoutParams) {
    ensureSubDecor();
    ((ViewGroup)this.mSubDecor.findViewById(16908290)).addView(paramView, paramLayoutParams);
    this.mOriginalWindowCallback.onContentChanged();
  }
  
  public boolean applyDayNight() {
    boolean bool = false;
    int i = getNightMode();
    int j = mapNightMode(i);
    if (j != -1)
      bool = updateForNightMode(j); 
    if (i == 0) {
      ensureAutoNightModeManager();
      this.mAutoNightModeManager.setup();
    } 
    this.mApplyDayNightCalled = true;
    return bool;
  }
  
  void callOnPanelClosed(int paramInt, PanelFeatureState paramPanelFeatureState, Menu paramMenu) {
    MenuBuilder menuBuilder;
    PanelFeatureState panelFeatureState = paramPanelFeatureState;
    Menu menu = paramMenu;
    if (paramMenu == null) {
      PanelFeatureState panelFeatureState1 = paramPanelFeatureState;
      if (paramPanelFeatureState == null) {
        panelFeatureState1 = paramPanelFeatureState;
        if (paramInt >= 0) {
          PanelFeatureState[] arrayOfPanelFeatureState = this.mPanels;
          panelFeatureState1 = paramPanelFeatureState;
          if (paramInt < arrayOfPanelFeatureState.length)
            panelFeatureState1 = arrayOfPanelFeatureState[paramInt]; 
        } 
      } 
      panelFeatureState = panelFeatureState1;
      menu = paramMenu;
      if (panelFeatureState1 != null) {
        menuBuilder = panelFeatureState1.menu;
        panelFeatureState = panelFeatureState1;
      } 
    } 
    if (panelFeatureState != null && !panelFeatureState.isOpen)
      return; 
    if (!this.mIsDestroyed)
      this.mOriginalWindowCallback.onPanelClosed(paramInt, (Menu)menuBuilder); 
  }
  
  void checkCloseActionMenu(MenuBuilder paramMenuBuilder) {
    if (this.mClosingActionMenu)
      return; 
    this.mClosingActionMenu = true;
    this.mDecorContentParent.dismissPopups();
    Window.Callback callback = getWindowCallback();
    if (callback != null && !this.mIsDestroyed)
      callback.onPanelClosed(108, (Menu)paramMenuBuilder); 
    this.mClosingActionMenu = false;
  }
  
  void closePanel(int paramInt) {
    closePanel(getPanelState(paramInt, true), true);
  }
  
  void closePanel(PanelFeatureState paramPanelFeatureState, boolean paramBoolean) {
    if (paramBoolean && paramPanelFeatureState.featureId == 0) {
      DecorContentParent decorContentParent = this.mDecorContentParent;
      if (decorContentParent != null && decorContentParent.isOverflowMenuShowing()) {
        checkCloseActionMenu(paramPanelFeatureState.menu);
        return;
      } 
    } 
    WindowManager windowManager = (WindowManager)this.mContext.getSystemService("window");
    if (windowManager != null && paramPanelFeatureState.isOpen && paramPanelFeatureState.decorView != null) {
      windowManager.removeView((View)paramPanelFeatureState.decorView);
      if (paramBoolean)
        callOnPanelClosed(paramPanelFeatureState.featureId, paramPanelFeatureState, null); 
    } 
    paramPanelFeatureState.isPrepared = false;
    paramPanelFeatureState.isHandled = false;
    paramPanelFeatureState.isOpen = false;
    paramPanelFeatureState.shownPanelView = null;
    paramPanelFeatureState.refreshDecorView = true;
    if (this.mPreparedPanel == paramPanelFeatureState)
      this.mPreparedPanel = null; 
  }
  
  public View createView(View paramView, String paramString, Context paramContext, AttributeSet paramAttributeSet) {
    AppCompatViewInflater appCompatViewInflater = this.mAppCompatViewInflater;
    boolean bool1 = false;
    if (appCompatViewInflater == null) {
      String str = this.mContext.obtainStyledAttributes(R.styleable.AppCompatTheme).getString(R.styleable.AppCompatTheme_viewInflaterClass);
      if (str == null || AppCompatViewInflater.class.getName().equals(str)) {
        this.mAppCompatViewInflater = new AppCompatViewInflater();
      } else {
        try {
          this.mAppCompatViewInflater = Class.forName(str).getDeclaredConstructor(new Class[0]).newInstance(new Object[0]);
        } finally {
          Exception exception = null;
          StringBuilder stringBuilder = new StringBuilder();
          stringBuilder.append("Failed to instantiate custom view inflater ");
          stringBuilder.append(str);
          stringBuilder.append(". Falling back to default.");
          Log.i("AppCompatDelegate", stringBuilder.toString(), exception);
        } 
      } 
    } 
    boolean bool2 = false;
    if (IS_PRE_LOLLIPOP)
      if (paramAttributeSet instanceof XmlPullParser) {
        bool2 = bool1;
        if (((XmlPullParser)paramAttributeSet).getDepth() > 1)
          bool2 = true; 
      } else {
        bool2 = shouldInheritContext((ViewParent)paramView);
      }  
    return this.mAppCompatViewInflater.createView(paramView, paramString, paramContext, paramAttributeSet, bool2, IS_PRE_LOLLIPOP, true, VectorEnabledTintResources.shouldBeUsed());
  }
  
  void dismissPopups() {
    DecorContentParent decorContentParent = this.mDecorContentParent;
    if (decorContentParent != null)
      decorContentParent.dismissPopups(); 
    if (this.mActionModePopup != null) {
      this.mWindow.getDecorView().removeCallbacks(this.mShowActionModePopup);
      if (this.mActionModePopup.isShowing())
        try {
          this.mActionModePopup.dismiss();
        } catch (IllegalArgumentException illegalArgumentException) {} 
      this.mActionModePopup = null;
    } 
    endOnGoingFadeAnimation();
    PanelFeatureState panelFeatureState = getPanelState(0, false);
    if (panelFeatureState != null && panelFeatureState.menu != null)
      panelFeatureState.menu.close(); 
  }
  
  boolean dispatchKeyEvent(KeyEvent paramKeyEvent) {
    Window.Callback callback = this.mOriginalWindowCallback;
    boolean bool = callback instanceof KeyEventDispatcher.Component;
    boolean bool1 = true;
    if (bool || callback instanceof AppCompatDialog) {
      View view = this.mWindow.getDecorView();
      if (view != null && KeyEventDispatcher.dispatchBeforeHierarchy(view, paramKeyEvent))
        return true; 
    } 
    if (paramKeyEvent.getKeyCode() == 82 && this.mOriginalWindowCallback.dispatchKeyEvent(paramKeyEvent))
      return true; 
    int i = paramKeyEvent.getKeyCode();
    if (paramKeyEvent.getAction() != 0)
      bool1 = false; 
    if (bool1) {
      bool = onKeyDown(i, paramKeyEvent);
    } else {
      bool = onKeyUp(i, paramKeyEvent);
    } 
    return bool;
  }
  
  void doInvalidatePanelMenu(int paramInt) {
    PanelFeatureState panelFeatureState = getPanelState(paramInt, true);
    if (panelFeatureState.menu != null) {
      Bundle bundle = new Bundle();
      panelFeatureState.menu.saveActionViewStates(bundle);
      if (bundle.size() > 0)
        panelFeatureState.frozenActionViewState = bundle; 
      panelFeatureState.menu.stopDispatchingItemsChanged();
      panelFeatureState.menu.clear();
    } 
    panelFeatureState.refreshMenuContent = true;
    panelFeatureState.refreshDecorView = true;
    if ((paramInt == 108 || paramInt == 0) && this.mDecorContentParent != null) {
      panelFeatureState = getPanelState(0, false);
      if (panelFeatureState != null) {
        panelFeatureState.isPrepared = false;
        preparePanel(panelFeatureState, null);
      } 
    } 
  }
  
  void endOnGoingFadeAnimation() {
    ViewPropertyAnimatorCompat viewPropertyAnimatorCompat = this.mFadeAnim;
    if (viewPropertyAnimatorCompat != null)
      viewPropertyAnimatorCompat.cancel(); 
  }
  
  PanelFeatureState findMenuPanel(Menu paramMenu) {
    byte b1;
    PanelFeatureState[] arrayOfPanelFeatureState = this.mPanels;
    if (arrayOfPanelFeatureState != null) {
      b1 = arrayOfPanelFeatureState.length;
    } else {
      b1 = 0;
    } 
    for (byte b2 = 0; b2 < b1; b2++) {
      PanelFeatureState panelFeatureState = arrayOfPanelFeatureState[b2];
      if (panelFeatureState != null && panelFeatureState.menu == paramMenu)
        return panelFeatureState; 
    } 
    return null;
  }
  
  public <T extends View> T findViewById(int paramInt) {
    ensureSubDecor();
    return (T)this.mWindow.findViewById(paramInt);
  }
  
  final Context getActionBarThemedContext() {
    Context context1 = null;
    ActionBar actionBar = getSupportActionBar();
    if (actionBar != null)
      context1 = actionBar.getThemedContext(); 
    Context context2 = context1;
    if (context1 == null)
      context2 = this.mContext; 
    return context2;
  }
  
  final AutoNightModeManager getAutoNightModeManager() {
    ensureAutoNightModeManager();
    return this.mAutoNightModeManager;
  }
  
  public final ActionBarDrawerToggle.Delegate getDrawerToggleDelegate() {
    return new ActionBarDrawableToggleImpl();
  }
  
  public MenuInflater getMenuInflater() {
    if (this.mMenuInflater == null) {
      Context context;
      initWindowDecorActionBar();
      ActionBar actionBar = this.mActionBar;
      if (actionBar != null) {
        context = actionBar.getThemedContext();
      } else {
        context = this.mContext;
      } 
      this.mMenuInflater = (MenuInflater)new SupportMenuInflater(context);
    } 
    return this.mMenuInflater;
  }
  
  protected PanelFeatureState getPanelState(int paramInt, boolean paramBoolean) {
    // Byte code:
    //   0: aload_0
    //   1: getfield mPanels : [Landroid/support/v7/app/AppCompatDelegateImpl$PanelFeatureState;
    //   4: astore_3
    //   5: aload_3
    //   6: astore #4
    //   8: aload_3
    //   9: ifnull -> 22
    //   12: aload #4
    //   14: astore_3
    //   15: aload #4
    //   17: arraylength
    //   18: iload_1
    //   19: if_icmpgt -> 56
    //   22: iload_1
    //   23: iconst_1
    //   24: iadd
    //   25: anewarray android/support/v7/app/AppCompatDelegateImpl$PanelFeatureState
    //   28: astore #5
    //   30: aload #4
    //   32: ifnull -> 47
    //   35: aload #4
    //   37: iconst_0
    //   38: aload #5
    //   40: iconst_0
    //   41: aload #4
    //   43: arraylength
    //   44: invokestatic arraycopy : (Ljava/lang/Object;ILjava/lang/Object;II)V
    //   47: aload #5
    //   49: astore_3
    //   50: aload_0
    //   51: aload #5
    //   53: putfield mPanels : [Landroid/support/v7/app/AppCompatDelegateImpl$PanelFeatureState;
    //   56: aload_3
    //   57: iload_1
    //   58: aaload
    //   59: astore #5
    //   61: aload #5
    //   63: astore #4
    //   65: aload #5
    //   67: ifnonnull -> 89
    //   70: new android/support/v7/app/AppCompatDelegateImpl$PanelFeatureState
    //   73: dup
    //   74: iload_1
    //   75: invokespecial <init> : (I)V
    //   78: astore #5
    //   80: aload #5
    //   82: astore #4
    //   84: aload_3
    //   85: iload_1
    //   86: aload #5
    //   88: aastore
    //   89: aload #4
    //   91: areturn
  }
  
  ViewGroup getSubDecor() {
    return this.mSubDecor;
  }
  
  public ActionBar getSupportActionBar() {
    initWindowDecorActionBar();
    return this.mActionBar;
  }
  
  final CharSequence getTitle() {
    Window.Callback callback = this.mOriginalWindowCallback;
    return (callback instanceof Activity) ? ((Activity)callback).getTitle() : this.mTitle;
  }
  
  final Window.Callback getWindowCallback() {
    return this.mWindow.getCallback();
  }
  
  public boolean hasWindowFeature(int paramInt) {
    boolean bool = false;
    int i = sanitizeWindowFeatureId(paramInt);
    boolean bool1 = true;
    if (i != 1) {
      if (i != 2) {
        if (i != 5) {
          if (i != 10) {
            if (i != 108) {
              if (i == 109)
                bool = this.mOverlayActionBar; 
            } else {
              bool = this.mHasActionBar;
            } 
          } else {
            bool = this.mOverlayActionMode;
          } 
        } else {
          bool = this.mFeatureIndeterminateProgress;
        } 
      } else {
        bool = this.mFeatureProgress;
      } 
    } else {
      bool = this.mWindowNoTitle;
    } 
    boolean bool2 = bool1;
    if (!bool)
      if (this.mWindow.hasFeature(paramInt)) {
        bool2 = bool1;
      } else {
        bool2 = false;
      }  
    return bool2;
  }
  
  public void installViewFactory() {
    LayoutInflater layoutInflater = LayoutInflater.from(this.mContext);
    if (layoutInflater.getFactory() == null) {
      LayoutInflaterCompat.setFactory2(layoutInflater, this);
    } else if (!(layoutInflater.getFactory2() instanceof AppCompatDelegateImpl)) {
      Log.i("AppCompatDelegate", "The Activity's LayoutInflater already has a Factory installed so we can not install AppCompat's");
    } 
  }
  
  public void invalidateOptionsMenu() {
    ActionBar actionBar = getSupportActionBar();
    if (actionBar != null && actionBar.invalidateOptionsMenu())
      return; 
    invalidatePanelMenu(0);
  }
  
  public boolean isHandleNativeActionModesEnabled() {
    return this.mHandleNativeActionModes;
  }
  
  int mapNightMode(int paramInt) {
    if (paramInt != -100) {
      if (paramInt != 0)
        return paramInt; 
      if (Build.VERSION.SDK_INT >= 23 && ((UiModeManager)this.mContext.getSystemService(UiModeManager.class)).getNightMode() == 0)
        return -1; 
      ensureAutoNightModeManager();
      return this.mAutoNightModeManager.getApplyableNightMode();
    } 
    return -1;
  }
  
  boolean onBackPressed() {
    ActionMode actionMode = this.mActionMode;
    if (actionMode != null) {
      actionMode.finish();
      return true;
    } 
    ActionBar actionBar = getSupportActionBar();
    return (actionBar != null && actionBar.collapseActionView());
  }
  
  public void onConfigurationChanged(Configuration paramConfiguration) {
    if (this.mHasActionBar && this.mSubDecorInstalled) {
      ActionBar actionBar = getSupportActionBar();
      if (actionBar != null)
        actionBar.onConfigurationChanged(paramConfiguration); 
    } 
    AppCompatDrawableManager.get().onConfigurationChanged(this.mContext);
    applyDayNight();
  }
  
  public void onCreate(Bundle paramBundle) {
    Window.Callback callback = this.mOriginalWindowCallback;
    if (callback instanceof Activity) {
      String str = null;
      try {
        String str1 = NavUtils.getParentActivityName((Activity)callback);
        str = str1;
      } catch (IllegalArgumentException illegalArgumentException) {}
      if (str != null) {
        ActionBar actionBar = peekSupportActionBar();
        if (actionBar == null) {
          this.mEnableDefaultActionBarUp = true;
        } else {
          actionBar.setDefaultDisplayHomeAsUpEnabled(true);
        } 
      } 
    } 
    if (paramBundle != null && this.mLocalNightMode == -100)
      this.mLocalNightMode = paramBundle.getInt("appcompat:local_night_mode", -100); 
  }
  
  public final View onCreateView(View paramView, String paramString, Context paramContext, AttributeSet paramAttributeSet) {
    return createView(paramView, paramString, paramContext, paramAttributeSet);
  }
  
  public View onCreateView(String paramString, Context paramContext, AttributeSet paramAttributeSet) {
    return onCreateView(null, paramString, paramContext, paramAttributeSet);
  }
  
  public void onDestroy() {
    if (this.mInvalidatePanelMenuPosted)
      this.mWindow.getDecorView().removeCallbacks(this.mInvalidatePanelMenuRunnable); 
    this.mIsDestroyed = true;
    ActionBar actionBar = this.mActionBar;
    if (actionBar != null)
      actionBar.onDestroy(); 
    AutoNightModeManager autoNightModeManager = this.mAutoNightModeManager;
    if (autoNightModeManager != null)
      autoNightModeManager.cleanup(); 
  }
  
  boolean onKeyDown(int paramInt, KeyEvent paramKeyEvent) {
    boolean bool = true;
    if (paramInt != 4) {
      if (paramInt == 82) {
        onKeyDownPanel(0, paramKeyEvent);
        return true;
      } 
    } else {
      if ((paramKeyEvent.getFlags() & 0x80) == 0)
        bool = false; 
      this.mLongPressBackDown = bool;
    } 
    return false;
  }
  
  boolean onKeyShortcut(int paramInt, KeyEvent paramKeyEvent) {
    PanelFeatureState panelFeatureState1;
    ActionBar actionBar = getSupportActionBar();
    if (actionBar != null && actionBar.onKeyShortcut(paramInt, paramKeyEvent))
      return true; 
    PanelFeatureState panelFeatureState2 = this.mPreparedPanel;
    if (panelFeatureState2 != null && performPanelShortcut(panelFeatureState2, paramKeyEvent.getKeyCode(), paramKeyEvent, 1)) {
      panelFeatureState1 = this.mPreparedPanel;
      if (panelFeatureState1 != null)
        panelFeatureState1.isHandled = true; 
      return true;
    } 
    if (this.mPreparedPanel == null) {
      panelFeatureState2 = getPanelState(0, true);
      preparePanel(panelFeatureState2, (KeyEvent)panelFeatureState1);
      boolean bool = performPanelShortcut(panelFeatureState2, panelFeatureState1.getKeyCode(), (KeyEvent)panelFeatureState1, 1);
      panelFeatureState2.isPrepared = false;
      if (bool)
        return true; 
    } 
    return false;
  }
  
  boolean onKeyUp(int paramInt, KeyEvent paramKeyEvent) {
    if (paramInt != 4) {
      if (paramInt == 82) {
        onKeyUpPanel(0, paramKeyEvent);
        return true;
      } 
    } else {
      boolean bool = this.mLongPressBackDown;
      this.mLongPressBackDown = false;
      PanelFeatureState panelFeatureState = getPanelState(0, false);
      if (panelFeatureState != null && panelFeatureState.isOpen) {
        if (!bool)
          closePanel(panelFeatureState, true); 
        return true;
      } 
      if (onBackPressed())
        return true; 
    } 
    return false;
  }
  
  public boolean onMenuItemSelected(MenuBuilder paramMenuBuilder, MenuItem paramMenuItem) {
    Window.Callback callback = getWindowCallback();
    if (callback != null && !this.mIsDestroyed) {
      PanelFeatureState panelFeatureState = findMenuPanel((Menu)paramMenuBuilder.getRootMenu());
      if (panelFeatureState != null)
        return callback.onMenuItemSelected(panelFeatureState.featureId, paramMenuItem); 
    } 
    return false;
  }
  
  public void onMenuModeChange(MenuBuilder paramMenuBuilder) {
    reopenMenu(paramMenuBuilder, true);
  }
  
  void onMenuOpened(int paramInt) {
    if (paramInt == 108) {
      ActionBar actionBar = getSupportActionBar();
      if (actionBar != null)
        actionBar.dispatchMenuVisibilityChanged(true); 
    } 
  }
  
  void onPanelClosed(int paramInt) {
    if (paramInt == 108) {
      ActionBar actionBar = getSupportActionBar();
      if (actionBar != null)
        actionBar.dispatchMenuVisibilityChanged(false); 
    } else if (paramInt == 0) {
      PanelFeatureState panelFeatureState = getPanelState(paramInt, true);
      if (panelFeatureState.isOpen)
        closePanel(panelFeatureState, false); 
    } 
  }
  
  public void onPostCreate(Bundle paramBundle) {
    ensureSubDecor();
  }
  
  public void onPostResume() {
    ActionBar actionBar = getSupportActionBar();
    if (actionBar != null)
      actionBar.setShowHideAnimationEnabled(true); 
  }
  
  public void onSaveInstanceState(Bundle paramBundle) {
    int i = this.mLocalNightMode;
    if (i != -100)
      paramBundle.putInt("appcompat:local_night_mode", i); 
  }
  
  public void onStart() {
    applyDayNight();
  }
  
  public void onStop() {
    ActionBar actionBar = getSupportActionBar();
    if (actionBar != null)
      actionBar.setShowHideAnimationEnabled(false); 
    AutoNightModeManager autoNightModeManager = this.mAutoNightModeManager;
    if (autoNightModeManager != null)
      autoNightModeManager.cleanup(); 
  }
  
  void onSubDecorInstalled(ViewGroup paramViewGroup) {}
  
  final ActionBar peekSupportActionBar() {
    return this.mActionBar;
  }
  
  public boolean requestWindowFeature(int paramInt) {
    paramInt = sanitizeWindowFeatureId(paramInt);
    if (this.mWindowNoTitle && paramInt == 108)
      return false; 
    if (this.mHasActionBar && paramInt == 1)
      this.mHasActionBar = false; 
    if (paramInt != 1) {
      if (paramInt != 2) {
        if (paramInt != 5) {
          if (paramInt != 10) {
            if (paramInt != 108) {
              if (paramInt != 109)
                return this.mWindow.requestFeature(paramInt); 
              throwFeatureRequestIfSubDecorInstalled();
              this.mOverlayActionBar = true;
              return true;
            } 
            throwFeatureRequestIfSubDecorInstalled();
            this.mHasActionBar = true;
            return true;
          } 
          throwFeatureRequestIfSubDecorInstalled();
          this.mOverlayActionMode = true;
          return true;
        } 
        throwFeatureRequestIfSubDecorInstalled();
        this.mFeatureIndeterminateProgress = true;
        return true;
      } 
      throwFeatureRequestIfSubDecorInstalled();
      this.mFeatureProgress = true;
      return true;
    } 
    throwFeatureRequestIfSubDecorInstalled();
    this.mWindowNoTitle = true;
    return true;
  }
  
  public void setContentView(int paramInt) {
    ensureSubDecor();
    ViewGroup viewGroup = (ViewGroup)this.mSubDecor.findViewById(16908290);
    viewGroup.removeAllViews();
    LayoutInflater.from(this.mContext).inflate(paramInt, viewGroup);
    this.mOriginalWindowCallback.onContentChanged();
  }
  
  public void setContentView(View paramView) {
    ensureSubDecor();
    ViewGroup viewGroup = (ViewGroup)this.mSubDecor.findViewById(16908290);
    viewGroup.removeAllViews();
    viewGroup.addView(paramView);
    this.mOriginalWindowCallback.onContentChanged();
  }
  
  public void setContentView(View paramView, ViewGroup.LayoutParams paramLayoutParams) {
    ensureSubDecor();
    ViewGroup viewGroup = (ViewGroup)this.mSubDecor.findViewById(16908290);
    viewGroup.removeAllViews();
    viewGroup.addView(paramView, paramLayoutParams);
    this.mOriginalWindowCallback.onContentChanged();
  }
  
  public void setHandleNativeActionModesEnabled(boolean paramBoolean) {
    this.mHandleNativeActionModes = paramBoolean;
  }
  
  public void setLocalNightMode(int paramInt) {
    if (paramInt != -1 && paramInt != 0 && paramInt != 1 && paramInt != 2) {
      Log.i("AppCompatDelegate", "setLocalNightMode() called with an unknown mode");
    } else if (this.mLocalNightMode != paramInt) {
      this.mLocalNightMode = paramInt;
      if (this.mApplyDayNightCalled)
        applyDayNight(); 
    } 
  }
  
  public void setSupportActionBar(Toolbar paramToolbar) {
    if (!(this.mOriginalWindowCallback instanceof Activity))
      return; 
    ActionBar actionBar = getSupportActionBar();
    if (!(actionBar instanceof WindowDecorActionBar)) {
      this.mMenuInflater = null;
      if (actionBar != null)
        actionBar.onDestroy(); 
      if (paramToolbar != null) {
        ToolbarActionBar toolbarActionBar = new ToolbarActionBar(paramToolbar, ((Activity)this.mOriginalWindowCallback).getTitle(), this.mAppCompatWindowCallback);
        this.mActionBar = toolbarActionBar;
        this.mWindow.setCallback(toolbarActionBar.getWrappedWindowCallback());
      } else {
        this.mActionBar = null;
        this.mWindow.setCallback(this.mAppCompatWindowCallback);
      } 
      invalidateOptionsMenu();
      return;
    } 
    throw new IllegalStateException("This Activity already has an action bar supplied by the window decor. Do not request Window.FEATURE_SUPPORT_ACTION_BAR and set windowActionBar to false in your theme to use a Toolbar instead.");
  }
  
  public final void setTitle(CharSequence paramCharSequence) {
    this.mTitle = paramCharSequence;
    DecorContentParent decorContentParent = this.mDecorContentParent;
    if (decorContentParent != null) {
      decorContentParent.setWindowTitle(paramCharSequence);
    } else if (peekSupportActionBar() != null) {
      peekSupportActionBar().setWindowTitle(paramCharSequence);
    } else {
      TextView textView = this.mTitleView;
      if (textView != null)
        textView.setText(paramCharSequence); 
    } 
  }
  
  final boolean shouldAnimateActionModeView() {
    if (this.mSubDecorInstalled) {
      ViewGroup viewGroup = this.mSubDecor;
      if (viewGroup != null && ViewCompat.isLaidOut((View)viewGroup))
        return true; 
    } 
    return false;
  }
  
  public ActionMode startSupportActionMode(ActionMode.Callback paramCallback) {
    if (paramCallback != null) {
      ActionMode actionMode = this.mActionMode;
      if (actionMode != null)
        actionMode.finish(); 
      paramCallback = new ActionModeCallbackWrapperV9(paramCallback);
      ActionBar actionBar = getSupportActionBar();
      if (actionBar != null) {
        ActionMode actionMode1 = actionBar.startActionMode(paramCallback);
        this.mActionMode = actionMode1;
        if (actionMode1 != null) {
          AppCompatCallback appCompatCallback = this.mAppCompatCallback;
          if (appCompatCallback != null)
            appCompatCallback.onSupportActionModeStarted(actionMode1); 
        } 
      } 
      if (this.mActionMode == null)
        this.mActionMode = startSupportActionModeFromWindow(paramCallback); 
      return this.mActionMode;
    } 
    throw new IllegalArgumentException("ActionMode callback can not be null.");
  }
  
  ActionMode startSupportActionModeFromWindow(ActionMode.Callback paramCallback) {
    ActionMode.Callback callback1;
    endOnGoingFadeAnimation();
    ActionMode actionMode2 = this.mActionMode;
    if (actionMode2 != null)
      actionMode2.finish(); 
    ActionMode.Callback callback2 = paramCallback;
    if (!(paramCallback instanceof ActionModeCallbackWrapperV9))
      callback2 = new ActionModeCallbackWrapperV9(paramCallback); 
    ActionMode.Callback callback3 = null;
    AppCompatCallback appCompatCallback = this.mAppCompatCallback;
    paramCallback = callback3;
    if (appCompatCallback != null) {
      paramCallback = callback3;
      if (!this.mIsDestroyed)
        try {
          ActionMode actionMode = appCompatCallback.onWindowStartingSupportActionMode(callback2);
        } catch (AbstractMethodError abstractMethodError) {
          callback1 = callback3;
        }  
    } 
    if (callback1 != null) {
      this.mActionMode = (ActionMode)callback1;
    } else {
      ActionBarContextView actionBarContextView = this.mActionModeView;
      boolean bool = true;
      if (actionBarContextView == null)
        if (this.mIsFloating) {
          Context context;
          TypedValue typedValue = new TypedValue();
          Resources.Theme theme = this.mContext.getTheme();
          theme.resolveAttribute(R.attr.actionBarTheme, typedValue, true);
          if (typedValue.resourceId != 0) {
            Resources.Theme theme1 = this.mContext.getResources().newTheme();
            theme1.setTo(theme);
            theme1.applyStyle(typedValue.resourceId, true);
            ContextThemeWrapper contextThemeWrapper = new ContextThemeWrapper(this.mContext, 0);
            contextThemeWrapper.getTheme().setTo(theme1);
          } else {
            context = this.mContext;
          } 
          this.mActionModeView = new ActionBarContextView(context);
          PopupWindow popupWindow = new PopupWindow(context, null, R.attr.actionModePopupWindowStyle);
          this.mActionModePopup = popupWindow;
          PopupWindowCompat.setWindowLayoutType(popupWindow, 2);
          this.mActionModePopup.setContentView((View)this.mActionModeView);
          this.mActionModePopup.setWidth(-1);
          context.getTheme().resolveAttribute(R.attr.actionBarSize, typedValue, true);
          int i = TypedValue.complexToDimensionPixelSize(typedValue.data, context.getResources().getDisplayMetrics());
          this.mActionModeView.setContentHeight(i);
          this.mActionModePopup.setHeight(-2);
          this.mShowActionModePopup = new Runnable() {
              public void run() {
                AppCompatDelegateImpl.this.mActionModePopup.showAtLocation((View)AppCompatDelegateImpl.this.mActionModeView, 55, 0, 0);
                AppCompatDelegateImpl.this.endOnGoingFadeAnimation();
                if (AppCompatDelegateImpl.this.shouldAnimateActionModeView()) {
                  AppCompatDelegateImpl.this.mActionModeView.setAlpha(0.0F);
                  AppCompatDelegateImpl appCompatDelegateImpl = AppCompatDelegateImpl.this;
                  appCompatDelegateImpl.mFadeAnim = ViewCompat.animate((View)appCompatDelegateImpl.mActionModeView).alpha(1.0F);
                  AppCompatDelegateImpl.this.mFadeAnim.setListener((ViewPropertyAnimatorListener)new ViewPropertyAnimatorListenerAdapter() {
                        public void onAnimationEnd(View param2View) {
                          AppCompatDelegateImpl.this.mActionModeView.setAlpha(1.0F);
                          AppCompatDelegateImpl.this.mFadeAnim.setListener(null);
                          AppCompatDelegateImpl.this.mFadeAnim = null;
                        }
                        
                        public void onAnimationStart(View param2View) {
                          AppCompatDelegateImpl.this.mActionModeView.setVisibility(0);
                        }
                      });
                } else {
                  AppCompatDelegateImpl.this.mActionModeView.setAlpha(1.0F);
                  AppCompatDelegateImpl.this.mActionModeView.setVisibility(0);
                } 
              }
            };
        } else {
          ViewStubCompat viewStubCompat = (ViewStubCompat)this.mSubDecor.findViewById(R.id.action_mode_bar_stub);
          if (viewStubCompat != null) {
            viewStubCompat.setLayoutInflater(LayoutInflater.from(getActionBarThemedContext()));
            this.mActionModeView = (ActionBarContextView)viewStubCompat.inflate();
          } 
        }  
      if (this.mActionModeView != null) {
        endOnGoingFadeAnimation();
        this.mActionModeView.killMode();
        Context context = this.mActionModeView.getContext();
        actionBarContextView = this.mActionModeView;
        if (this.mActionModePopup != null)
          bool = false; 
        StandaloneActionMode standaloneActionMode = new StandaloneActionMode(context, actionBarContextView, callback2, bool);
        if (callback2.onCreateActionMode((ActionMode)standaloneActionMode, standaloneActionMode.getMenu())) {
          standaloneActionMode.invalidate();
          this.mActionModeView.initForMode((ActionMode)standaloneActionMode);
          this.mActionMode = (ActionMode)standaloneActionMode;
          if (shouldAnimateActionModeView()) {
            this.mActionModeView.setAlpha(0.0F);
            ViewPropertyAnimatorCompat viewPropertyAnimatorCompat = ViewCompat.animate((View)this.mActionModeView).alpha(1.0F);
            this.mFadeAnim = viewPropertyAnimatorCompat;
            viewPropertyAnimatorCompat.setListener((ViewPropertyAnimatorListener)new ViewPropertyAnimatorListenerAdapter() {
                  public void onAnimationEnd(View param1View) {
                    AppCompatDelegateImpl.this.mActionModeView.setAlpha(1.0F);
                    AppCompatDelegateImpl.this.mFadeAnim.setListener(null);
                    AppCompatDelegateImpl.this.mFadeAnim = null;
                  }
                  
                  public void onAnimationStart(View param1View) {
                    AppCompatDelegateImpl.this.mActionModeView.setVisibility(0);
                    AppCompatDelegateImpl.this.mActionModeView.sendAccessibilityEvent(32);
                    if (AppCompatDelegateImpl.this.mActionModeView.getParent() instanceof View)
                      ViewCompat.requestApplyInsets((View)AppCompatDelegateImpl.this.mActionModeView.getParent()); 
                  }
                });
          } else {
            this.mActionModeView.setAlpha(1.0F);
            this.mActionModeView.setVisibility(0);
            this.mActionModeView.sendAccessibilityEvent(32);
            if (this.mActionModeView.getParent() instanceof View)
              ViewCompat.requestApplyInsets((View)this.mActionModeView.getParent()); 
          } 
          if (this.mActionModePopup != null)
            this.mWindow.getDecorView().post(this.mShowActionModePopup); 
        } else {
          this.mActionMode = null;
        } 
      } 
    } 
    ActionMode actionMode1 = this.mActionMode;
    if (actionMode1 != null) {
      AppCompatCallback appCompatCallback1 = this.mAppCompatCallback;
      if (appCompatCallback1 != null)
        appCompatCallback1.onSupportActionModeStarted(actionMode1); 
    } 
    return this.mActionMode;
  }
  
  int updateStatusGuard(int paramInt) {
    int i = 0;
    boolean bool1 = false;
    ActionBarContextView actionBarContextView = this.mActionModeView;
    boolean bool2 = false;
    int j = i;
    int k = paramInt;
    if (actionBarContextView != null) {
      j = i;
      k = paramInt;
      if (actionBarContextView.getLayoutParams() instanceof ViewGroup.MarginLayoutParams) {
        boolean bool;
        ViewGroup.MarginLayoutParams marginLayoutParams = (ViewGroup.MarginLayoutParams)this.mActionModeView.getLayoutParams();
        int m = 0;
        i = 0;
        if (this.mActionModeView.isShown()) {
          if (this.mTempRect1 == null) {
            this.mTempRect1 = new Rect();
            this.mTempRect2 = new Rect();
          } 
          Rect rect1 = this.mTempRect1;
          Rect rect2 = this.mTempRect2;
          rect1.set(0, paramInt, 0, 0);
          ViewUtils.computeFitSystemWindows((View)this.mSubDecor, rect1, rect2);
          if (rect2.top == 0) {
            bool = paramInt;
          } else {
            bool = false;
          } 
          if (marginLayoutParams.topMargin != bool) {
            bool = true;
            marginLayoutParams.topMargin = paramInt;
            View view1 = this.mStatusGuard;
            if (view1 == null) {
              view1 = new View(this.mContext);
              this.mStatusGuard = view1;
              view1.setBackgroundColor(this.mContext.getResources().getColor(R.color.abc_input_method_navigation_guard));
              this.mSubDecor.addView(this.mStatusGuard, -1, new ViewGroup.LayoutParams(-1, paramInt));
              i = bool;
            } else {
              ViewGroup.LayoutParams layoutParams = view1.getLayoutParams();
              i = bool;
              if (layoutParams.height != paramInt) {
                layoutParams.height = paramInt;
                this.mStatusGuard.setLayoutParams(layoutParams);
                i = bool;
              } 
            } 
          } 
          if (this.mStatusGuard != null) {
            bool = true;
          } else {
            bool = false;
          } 
          k = paramInt;
          if (!this.mOverlayActionMode) {
            k = paramInt;
            if (bool)
              k = 0; 
          } 
          m = i;
          i = k;
        } else {
          bool = bool1;
          i = paramInt;
          if (marginLayoutParams.topMargin != 0) {
            m = 1;
            marginLayoutParams.topMargin = 0;
            i = paramInt;
            bool = bool1;
          } 
        } 
        j = bool;
        k = i;
        if (m != 0) {
          this.mActionModeView.setLayoutParams((ViewGroup.LayoutParams)marginLayoutParams);
          k = i;
          j = bool;
        } 
      } 
    } 
    View view = this.mStatusGuard;
    if (view != null) {
      if (j != 0) {
        paramInt = bool2;
      } else {
        paramInt = 8;
      } 
      view.setVisibility(paramInt);
    } 
    return k;
  }
  
  static {
    boolean bool;
    if (Build.VERSION.SDK_INT < 21) {
      bool = true;
    } else {
      bool = false;
    } 
    IS_PRE_LOLLIPOP = bool;
  }
  
  private class ActionBarDrawableToggleImpl implements ActionBarDrawerToggle.Delegate {
    public Context getActionBarThemedContext() {
      return AppCompatDelegateImpl.this.getActionBarThemedContext();
    }
    
    public Drawable getThemeUpIndicator() {
      TintTypedArray tintTypedArray = TintTypedArray.obtainStyledAttributes(getActionBarThemedContext(), null, new int[] { R.attr.homeAsUpIndicator });
      Drawable drawable = tintTypedArray.getDrawable(0);
      tintTypedArray.recycle();
      return drawable;
    }
    
    public boolean isNavigationVisible() {
      boolean bool;
      ActionBar actionBar = AppCompatDelegateImpl.this.getSupportActionBar();
      if (actionBar != null && (actionBar.getDisplayOptions() & 0x4) != 0) {
        bool = true;
      } else {
        bool = false;
      } 
      return bool;
    }
    
    public void setActionBarDescription(int param1Int) {
      ActionBar actionBar = AppCompatDelegateImpl.this.getSupportActionBar();
      if (actionBar != null)
        actionBar.setHomeActionContentDescription(param1Int); 
    }
    
    public void setActionBarUpIndicator(Drawable param1Drawable, int param1Int) {
      ActionBar actionBar = AppCompatDelegateImpl.this.getSupportActionBar();
      if (actionBar != null) {
        actionBar.setHomeAsUpIndicator(param1Drawable);
        actionBar.setHomeActionContentDescription(param1Int);
      } 
    }
  }
  
  private final class ActionMenuPresenterCallback implements MenuPresenter.Callback {
    public void onCloseMenu(MenuBuilder param1MenuBuilder, boolean param1Boolean) {
      AppCompatDelegateImpl.this.checkCloseActionMenu(param1MenuBuilder);
    }
    
    public boolean onOpenSubMenu(MenuBuilder param1MenuBuilder) {
      Window.Callback callback = AppCompatDelegateImpl.this.getWindowCallback();
      if (callback != null)
        callback.onMenuOpened(108, (Menu)param1MenuBuilder); 
      return true;
    }
  }
  
  class ActionModeCallbackWrapperV9 implements ActionMode.Callback {
    private ActionMode.Callback mWrapped;
    
    public ActionModeCallbackWrapperV9(ActionMode.Callback param1Callback) {
      this.mWrapped = param1Callback;
    }
    
    public boolean onActionItemClicked(ActionMode param1ActionMode, MenuItem param1MenuItem) {
      return this.mWrapped.onActionItemClicked(param1ActionMode, param1MenuItem);
    }
    
    public boolean onCreateActionMode(ActionMode param1ActionMode, Menu param1Menu) {
      return this.mWrapped.onCreateActionMode(param1ActionMode, param1Menu);
    }
    
    public void onDestroyActionMode(ActionMode param1ActionMode) {
      this.mWrapped.onDestroyActionMode(param1ActionMode);
      if (AppCompatDelegateImpl.this.mActionModePopup != null)
        AppCompatDelegateImpl.this.mWindow.getDecorView().removeCallbacks(AppCompatDelegateImpl.this.mShowActionModePopup); 
      if (AppCompatDelegateImpl.this.mActionModeView != null) {
        AppCompatDelegateImpl.this.endOnGoingFadeAnimation();
        AppCompatDelegateImpl appCompatDelegateImpl = AppCompatDelegateImpl.this;
        appCompatDelegateImpl.mFadeAnim = ViewCompat.animate((View)appCompatDelegateImpl.mActionModeView).alpha(0.0F);
        AppCompatDelegateImpl.this.mFadeAnim.setListener((ViewPropertyAnimatorListener)new ViewPropertyAnimatorListenerAdapter() {
              public void onAnimationEnd(View param2View) {
                AppCompatDelegateImpl.this.mActionModeView.setVisibility(8);
                if (AppCompatDelegateImpl.this.mActionModePopup != null) {
                  AppCompatDelegateImpl.this.mActionModePopup.dismiss();
                } else if (AppCompatDelegateImpl.this.mActionModeView.getParent() instanceof View) {
                  ViewCompat.requestApplyInsets((View)AppCompatDelegateImpl.this.mActionModeView.getParent());
                } 
                AppCompatDelegateImpl.this.mActionModeView.removeAllViews();
                AppCompatDelegateImpl.this.mFadeAnim.setListener(null);
                AppCompatDelegateImpl.this.mFadeAnim = null;
              }
            });
      } 
      if (AppCompatDelegateImpl.this.mAppCompatCallback != null)
        AppCompatDelegateImpl.this.mAppCompatCallback.onSupportActionModeFinished(AppCompatDelegateImpl.this.mActionMode); 
      AppCompatDelegateImpl.this.mActionMode = null;
    }
    
    public boolean onPrepareActionMode(ActionMode param1ActionMode, Menu param1Menu) {
      return this.mWrapped.onPrepareActionMode(param1ActionMode, param1Menu);
    }
  }
  
  class null extends ViewPropertyAnimatorListenerAdapter {
    public void onAnimationEnd(View param1View) {
      AppCompatDelegateImpl.this.mActionModeView.setVisibility(8);
      if (AppCompatDelegateImpl.this.mActionModePopup != null) {
        AppCompatDelegateImpl.this.mActionModePopup.dismiss();
      } else if (AppCompatDelegateImpl.this.mActionModeView.getParent() instanceof View) {
        ViewCompat.requestApplyInsets((View)AppCompatDelegateImpl.this.mActionModeView.getParent());
      } 
      AppCompatDelegateImpl.this.mActionModeView.removeAllViews();
      AppCompatDelegateImpl.this.mFadeAnim.setListener(null);
      AppCompatDelegateImpl.this.mFadeAnim = null;
    }
  }
  
  class AppCompatWindowCallback extends WindowCallbackWrapper {
    AppCompatWindowCallback(Window.Callback param1Callback) {
      super(param1Callback);
    }
    
    public boolean dispatchKeyEvent(KeyEvent param1KeyEvent) {
      return (AppCompatDelegateImpl.this.dispatchKeyEvent(param1KeyEvent) || super.dispatchKeyEvent(param1KeyEvent));
    }
    
    public boolean dispatchKeyShortcutEvent(KeyEvent param1KeyEvent) {
      return (super.dispatchKeyShortcutEvent(param1KeyEvent) || AppCompatDelegateImpl.this.onKeyShortcut(param1KeyEvent.getKeyCode(), param1KeyEvent));
    }
    
    public void onContentChanged() {}
    
    public boolean onCreatePanelMenu(int param1Int, Menu param1Menu) {
      return (param1Int == 0 && !(param1Menu instanceof MenuBuilder)) ? false : super.onCreatePanelMenu(param1Int, param1Menu);
    }
    
    public boolean onMenuOpened(int param1Int, Menu param1Menu) {
      super.onMenuOpened(param1Int, param1Menu);
      AppCompatDelegateImpl.this.onMenuOpened(param1Int);
      return true;
    }
    
    public void onPanelClosed(int param1Int, Menu param1Menu) {
      super.onPanelClosed(param1Int, param1Menu);
      AppCompatDelegateImpl.this.onPanelClosed(param1Int);
    }
    
    public boolean onPreparePanel(int param1Int, View param1View, Menu param1Menu) {
      MenuBuilder menuBuilder;
      if (param1Menu instanceof MenuBuilder) {
        menuBuilder = (MenuBuilder)param1Menu;
      } else {
        menuBuilder = null;
      } 
      if (param1Int == 0 && menuBuilder == null)
        return false; 
      if (menuBuilder != null)
        menuBuilder.setOverrideVisibleItems(true); 
      boolean bool = super.onPreparePanel(param1Int, param1View, param1Menu);
      if (menuBuilder != null)
        menuBuilder.setOverrideVisibleItems(false); 
      return bool;
    }
    
    public void onProvideKeyboardShortcuts(List<KeyboardShortcutGroup> param1List, Menu param1Menu, int param1Int) {
      AppCompatDelegateImpl.PanelFeatureState panelFeatureState = AppCompatDelegateImpl.this.getPanelState(0, true);
      if (panelFeatureState != null && panelFeatureState.menu != null) {
        super.onProvideKeyboardShortcuts(param1List, (Menu)panelFeatureState.menu, param1Int);
      } else {
        super.onProvideKeyboardShortcuts(param1List, param1Menu, param1Int);
      } 
    }
    
    public ActionMode onWindowStartingActionMode(ActionMode.Callback param1Callback) {
      return (Build.VERSION.SDK_INT >= 23) ? null : (AppCompatDelegateImpl.this.isHandleNativeActionModesEnabled() ? startAsSupportActionMode(param1Callback) : super.onWindowStartingActionMode(param1Callback));
    }
    
    public ActionMode onWindowStartingActionMode(ActionMode.Callback param1Callback, int param1Int) {
      return (!AppCompatDelegateImpl.this.isHandleNativeActionModesEnabled() || param1Int != 0) ? super.onWindowStartingActionMode(param1Callback, param1Int) : startAsSupportActionMode(param1Callback);
    }
    
    final ActionMode startAsSupportActionMode(ActionMode.Callback param1Callback) {
      SupportActionModeWrapper.CallbackWrapper callbackWrapper = new SupportActionModeWrapper.CallbackWrapper(AppCompatDelegateImpl.this.mContext, param1Callback);
      ActionMode actionMode = AppCompatDelegateImpl.this.startSupportActionMode((ActionMode.Callback)callbackWrapper);
      return (actionMode != null) ? callbackWrapper.getActionModeWrapper(actionMode) : null;
    }
  }
  
  final class AutoNightModeManager {
    private BroadcastReceiver mAutoTimeChangeReceiver;
    
    private IntentFilter mAutoTimeChangeReceiverFilter;
    
    private boolean mIsNight;
    
    private TwilightManager mTwilightManager;
    
    AutoNightModeManager(TwilightManager param1TwilightManager) {
      this.mTwilightManager = param1TwilightManager;
      this.mIsNight = param1TwilightManager.isNight();
    }
    
    void cleanup() {
      if (this.mAutoTimeChangeReceiver != null) {
        AppCompatDelegateImpl.this.mContext.unregisterReceiver(this.mAutoTimeChangeReceiver);
        this.mAutoTimeChangeReceiver = null;
      } 
    }
    
    void dispatchTimeChanged() {
      boolean bool = this.mTwilightManager.isNight();
      if (bool != this.mIsNight) {
        this.mIsNight = bool;
        AppCompatDelegateImpl.this.applyDayNight();
      } 
    }
    
    int getApplyableNightMode() {
      boolean bool1;
      boolean bool = this.mTwilightManager.isNight();
      this.mIsNight = bool;
      if (bool) {
        bool1 = true;
      } else {
        bool1 = true;
      } 
      return bool1;
    }
    
    void setup() {
      cleanup();
      if (this.mAutoTimeChangeReceiver == null)
        this.mAutoTimeChangeReceiver = new BroadcastReceiver() {
            public void onReceive(Context param2Context, Intent param2Intent) {
              AppCompatDelegateImpl.AutoNightModeManager.this.dispatchTimeChanged();
            }
          }; 
      if (this.mAutoTimeChangeReceiverFilter == null) {
        IntentFilter intentFilter = new IntentFilter();
        this.mAutoTimeChangeReceiverFilter = intentFilter;
        intentFilter.addAction("android.intent.action.TIME_SET");
        this.mAutoTimeChangeReceiverFilter.addAction("android.intent.action.TIMEZONE_CHANGED");
        this.mAutoTimeChangeReceiverFilter.addAction("android.intent.action.TIME_TICK");
      } 
      AppCompatDelegateImpl.this.mContext.registerReceiver(this.mAutoTimeChangeReceiver, this.mAutoTimeChangeReceiverFilter);
    }
  }
  
  class null extends BroadcastReceiver {
    public void onReceive(Context param1Context, Intent param1Intent) {
      this.this$1.dispatchTimeChanged();
    }
  }
  
  private class ListMenuDecorView extends ContentFrameLayout {
    public ListMenuDecorView(Context param1Context) {
      super(param1Context);
    }
    
    private boolean isOutOfBounds(int param1Int1, int param1Int2) {
      return (param1Int1 < -5 || param1Int2 < -5 || param1Int1 > getWidth() + 5 || param1Int2 > getHeight() + 5);
    }
    
    public boolean dispatchKeyEvent(KeyEvent param1KeyEvent) {
      return (AppCompatDelegateImpl.this.dispatchKeyEvent(param1KeyEvent) || super.dispatchKeyEvent(param1KeyEvent));
    }
    
    public boolean onInterceptTouchEvent(MotionEvent param1MotionEvent) {
      if (param1MotionEvent.getAction() == 0 && isOutOfBounds((int)param1MotionEvent.getX(), (int)param1MotionEvent.getY())) {
        AppCompatDelegateImpl.this.closePanel(0);
        return true;
      } 
      return super.onInterceptTouchEvent(param1MotionEvent);
    }
    
    public void setBackgroundResource(int param1Int) {
      setBackgroundDrawable(AppCompatResources.getDrawable(getContext(), param1Int));
    }
  }
  
  protected static final class PanelFeatureState {
    int background;
    
    View createdPanelView;
    
    ViewGroup decorView;
    
    int featureId;
    
    Bundle frozenActionViewState;
    
    Bundle frozenMenuState;
    
    int gravity;
    
    boolean isHandled;
    
    boolean isOpen;
    
    boolean isPrepared;
    
    ListMenuPresenter listMenuPresenter;
    
    Context listPresenterContext;
    
    MenuBuilder menu;
    
    public boolean qwertyMode;
    
    boolean refreshDecorView;
    
    boolean refreshMenuContent;
    
    View shownPanelView;
    
    boolean wasLastOpen;
    
    int windowAnimations;
    
    int x;
    
    int y;
    
    PanelFeatureState(int param1Int) {
      this.featureId = param1Int;
      this.refreshDecorView = false;
    }
    
    void applyFrozenState() {
      MenuBuilder menuBuilder = this.menu;
      if (menuBuilder != null) {
        Bundle bundle = this.frozenMenuState;
        if (bundle != null) {
          menuBuilder.restorePresenterStates(bundle);
          this.frozenMenuState = null;
        } 
      } 
    }
    
    public void clearMenuPresenters() {
      MenuBuilder menuBuilder = this.menu;
      if (menuBuilder != null)
        menuBuilder.removeMenuPresenter((MenuPresenter)this.listMenuPresenter); 
      this.listMenuPresenter = null;
    }
    
    MenuView getListMenuView(MenuPresenter.Callback param1Callback) {
      if (this.menu == null)
        return null; 
      if (this.listMenuPresenter == null) {
        ListMenuPresenter listMenuPresenter = new ListMenuPresenter(this.listPresenterContext, R.layout.abc_list_menu_item_layout);
        this.listMenuPresenter = listMenuPresenter;
        listMenuPresenter.setCallback(param1Callback);
        this.menu.addMenuPresenter((MenuPresenter)this.listMenuPresenter);
      } 
      return this.listMenuPresenter.getMenuView(this.decorView);
    }
    
    public boolean hasPanelItems() {
      View view = this.shownPanelView;
      boolean bool = false;
      if (view == null)
        return false; 
      if (this.createdPanelView != null)
        return true; 
      if (this.listMenuPresenter.getAdapter().getCount() > 0)
        bool = true; 
      return bool;
    }
    
    void onRestoreInstanceState(Parcelable param1Parcelable) {
      param1Parcelable = param1Parcelable;
      this.featureId = ((SavedState)param1Parcelable).featureId;
      this.wasLastOpen = ((SavedState)param1Parcelable).isOpen;
      this.frozenMenuState = ((SavedState)param1Parcelable).menuState;
      this.shownPanelView = null;
      this.decorView = null;
    }
    
    Parcelable onSaveInstanceState() {
      SavedState savedState = new SavedState();
      savedState.featureId = this.featureId;
      savedState.isOpen = this.isOpen;
      if (this.menu != null) {
        savedState.menuState = new Bundle();
        this.menu.savePresenterStates(savedState.menuState);
      } 
      return savedState;
    }
    
    void setMenu(MenuBuilder param1MenuBuilder) {
      MenuBuilder menuBuilder = this.menu;
      if (param1MenuBuilder == menuBuilder)
        return; 
      if (menuBuilder != null)
        menuBuilder.removeMenuPresenter((MenuPresenter)this.listMenuPresenter); 
      this.menu = param1MenuBuilder;
      if (param1MenuBuilder != null) {
        ListMenuPresenter listMenuPresenter = this.listMenuPresenter;
        if (listMenuPresenter != null)
          param1MenuBuilder.addMenuPresenter((MenuPresenter)listMenuPresenter); 
      } 
    }
    
    void setStyle(Context param1Context) {
      TypedValue typedValue = new TypedValue();
      Resources.Theme theme = param1Context.getResources().newTheme();
      theme.setTo(param1Context.getTheme());
      theme.resolveAttribute(R.attr.actionBarPopupTheme, typedValue, true);
      if (typedValue.resourceId != 0)
        theme.applyStyle(typedValue.resourceId, true); 
      theme.resolveAttribute(R.attr.panelMenuListTheme, typedValue, true);
      if (typedValue.resourceId != 0) {
        theme.applyStyle(typedValue.resourceId, true);
      } else {
        theme.applyStyle(R.style.Theme_AppCompat_CompactMenu, true);
      } 
      ContextThemeWrapper contextThemeWrapper = new ContextThemeWrapper(param1Context, 0);
      contextThemeWrapper.getTheme().setTo(theme);
      this.listPresenterContext = (Context)contextThemeWrapper;
      TypedArray typedArray = contextThemeWrapper.obtainStyledAttributes(R.styleable.AppCompatTheme);
      this.background = typedArray.getResourceId(R.styleable.AppCompatTheme_panelBackground, 0);
      this.windowAnimations = typedArray.getResourceId(R.styleable.AppCompatTheme_android_windowAnimationStyle, 0);
      typedArray.recycle();
    }
    
    private static class SavedState implements Parcelable {
      public static final Parcelable.Creator<SavedState> CREATOR = (Parcelable.Creator<SavedState>)new Parcelable.ClassLoaderCreator<SavedState>() {
          public AppCompatDelegateImpl.PanelFeatureState.SavedState createFromParcel(Parcel param3Parcel) {
            return AppCompatDelegateImpl.PanelFeatureState.SavedState.readFromParcel(param3Parcel, null);
          }
          
          public AppCompatDelegateImpl.PanelFeatureState.SavedState createFromParcel(Parcel param3Parcel, ClassLoader param3ClassLoader) {
            return AppCompatDelegateImpl.PanelFeatureState.SavedState.readFromParcel(param3Parcel, param3ClassLoader);
          }
          
          public AppCompatDelegateImpl.PanelFeatureState.SavedState[] newArray(int param3Int) {
            return new AppCompatDelegateImpl.PanelFeatureState.SavedState[param3Int];
          }
        };
      
      int featureId;
      
      boolean isOpen;
      
      Bundle menuState;
      
      static SavedState readFromParcel(Parcel param2Parcel, ClassLoader param2ClassLoader) {
        SavedState savedState = new SavedState();
        savedState.featureId = param2Parcel.readInt();
        int i = param2Parcel.readInt();
        boolean bool = true;
        if (i != 1)
          bool = false; 
        savedState.isOpen = bool;
        if (bool)
          savedState.menuState = param2Parcel.readBundle(param2ClassLoader); 
        return savedState;
      }
      
      public int describeContents() {
        return 0;
      }
      
      public void writeToParcel(Parcel param2Parcel, int param2Int) {
        param2Parcel.writeInt(this.featureId);
        param2Parcel.writeInt(this.isOpen);
        if (this.isOpen)
          param2Parcel.writeBundle(this.menuState); 
      }
    }
    
    static final class null implements Parcelable.ClassLoaderCreator<SavedState> {
      public AppCompatDelegateImpl.PanelFeatureState.SavedState createFromParcel(Parcel param2Parcel) {
        return AppCompatDelegateImpl.PanelFeatureState.SavedState.readFromParcel(param2Parcel, null);
      }
      
      public AppCompatDelegateImpl.PanelFeatureState.SavedState createFromParcel(Parcel param2Parcel, ClassLoader param2ClassLoader) {
        return AppCompatDelegateImpl.PanelFeatureState.SavedState.readFromParcel(param2Parcel, param2ClassLoader);
      }
      
      public AppCompatDelegateImpl.PanelFeatureState.SavedState[] newArray(int param2Int) {
        return new AppCompatDelegateImpl.PanelFeatureState.SavedState[param2Int];
      }
    }
  }
  
  private static class SavedState implements Parcelable {
    public static final Parcelable.Creator<SavedState> CREATOR = (Parcelable.Creator<SavedState>)new Parcelable.ClassLoaderCreator<SavedState>() {
        public AppCompatDelegateImpl.PanelFeatureState.SavedState createFromParcel(Parcel param3Parcel) {
          return AppCompatDelegateImpl.PanelFeatureState.SavedState.readFromParcel(param3Parcel, null);
        }
        
        public AppCompatDelegateImpl.PanelFeatureState.SavedState createFromParcel(Parcel param3Parcel, ClassLoader param3ClassLoader) {
          return AppCompatDelegateImpl.PanelFeatureState.SavedState.readFromParcel(param3Parcel, param3ClassLoader);
        }
        
        public AppCompatDelegateImpl.PanelFeatureState.SavedState[] newArray(int param3Int) {
          return new AppCompatDelegateImpl.PanelFeatureState.SavedState[param3Int];
        }
      };
    
    int featureId;
    
    boolean isOpen;
    
    Bundle menuState;
    
    static SavedState readFromParcel(Parcel param1Parcel, ClassLoader param1ClassLoader) {
      SavedState savedState = new SavedState();
      savedState.featureId = param1Parcel.readInt();
      int i = param1Parcel.readInt();
      boolean bool = true;
      if (i != 1)
        bool = false; 
      savedState.isOpen = bool;
      if (bool)
        savedState.menuState = param1Parcel.readBundle(param1ClassLoader); 
      return savedState;
    }
    
    public int describeContents() {
      return 0;
    }
    
    public void writeToParcel(Parcel param1Parcel, int param1Int) {
      param1Parcel.writeInt(this.featureId);
      param1Parcel.writeInt(this.isOpen);
      if (this.isOpen)
        param1Parcel.writeBundle(this.menuState); 
    }
  }
  
  static final class null implements Parcelable.ClassLoaderCreator<PanelFeatureState.SavedState> {
    public AppCompatDelegateImpl.PanelFeatureState.SavedState createFromParcel(Parcel param1Parcel) {
      return AppCompatDelegateImpl.PanelFeatureState.SavedState.readFromParcel(param1Parcel, null);
    }
    
    public AppCompatDelegateImpl.PanelFeatureState.SavedState createFromParcel(Parcel param1Parcel, ClassLoader param1ClassLoader) {
      return AppCompatDelegateImpl.PanelFeatureState.SavedState.readFromParcel(param1Parcel, param1ClassLoader);
    }
    
    public AppCompatDelegateImpl.PanelFeatureState.SavedState[] newArray(int param1Int) {
      return new AppCompatDelegateImpl.PanelFeatureState.SavedState[param1Int];
    }
  }
  
  private final class PanelMenuPresenterCallback implements MenuPresenter.Callback {
    public void onCloseMenu(MenuBuilder param1MenuBuilder, boolean param1Boolean) {
      boolean bool;
      MenuBuilder menuBuilder = param1MenuBuilder.getRootMenu();
      if (menuBuilder != param1MenuBuilder) {
        bool = true;
      } else {
        bool = false;
      } 
      AppCompatDelegateImpl appCompatDelegateImpl = AppCompatDelegateImpl.this;
      if (bool)
        param1MenuBuilder = menuBuilder; 
      AppCompatDelegateImpl.PanelFeatureState panelFeatureState = appCompatDelegateImpl.findMenuPanel((Menu)param1MenuBuilder);
      if (panelFeatureState != null)
        if (bool) {
          AppCompatDelegateImpl.this.callOnPanelClosed(panelFeatureState.featureId, panelFeatureState, (Menu)menuBuilder);
          AppCompatDelegateImpl.this.closePanel(panelFeatureState, true);
        } else {
          AppCompatDelegateImpl.this.closePanel(panelFeatureState, param1Boolean);
        }  
    }
    
    public boolean onOpenSubMenu(MenuBuilder param1MenuBuilder) {
      if (param1MenuBuilder == null && AppCompatDelegateImpl.this.mHasActionBar) {
        Window.Callback callback = AppCompatDelegateImpl.this.getWindowCallback();
        if (callback != null && !AppCompatDelegateImpl.this.mIsDestroyed)
          callback.onMenuOpened(108, (Menu)param1MenuBuilder); 
      } 
      return true;
    }
  }
}


/* Location:              /root/Downloads/trendmicro/mobile2/test/classes-dex2jar.jar!/android/support/v7/app/AppCompatDelegateImpl.class
 * Java compiler version: 8 (52.0)
 * JD-Core Version:       1.1.3
 */